Workbook

Sheet Cliente
B1: Chotocruz & Co. · Ficha de cliente
B3: Concepto | C3: Dato numérico | E3: Dato cualitativo
B5: Identificación
B6: Nombre | E6: Cliente de ejemplo
B7: Tipo de documento | E7: Cédula de identidad
B8: Cédula | E8: 1-1234-5678
B9: Fecha de nacimiento | E9: 1980-05-01
B10: Ocupación | E10: Gerente general
B11: Estado civil | E11: Casado(a)
B12: Correo electrónico | E12: ejemplo@ejemplo.com
B13: Teléfono | E13: +506 88887070
B14: País de residencia | E14: Costa Rica
B15: Provincia | E15: Alajuela
B16: Cantón | E16: San Ramón
B17: Distrito | E17: Santiago
B18: Otras señas | E18: —
B19: Edad actual | C19: 46
B20: Edad de independencia financiera | C20: 60
B22: Perfil de riesgo (cuestionario 1)
B23: Tolerancia al riesgo (0 a 10) | C23: 3.0928571 | E23: Preguntas 1, 2, 3, 7 y 9
B24: Apetito de riesgo (0 a 10) | C24: 4.68625 | E24: Preguntas 4, 5, 6, 8 y 10
B25: Puntaje del perfil de riesgo (0 a 10) | C25: 3.9426667
B26: Perfil de riesgo | E26: Moderado conservador
B28: Activos y pasivos (US$, sin la vivienda principal)
B29: Activo: Portafolio de inversión (este portafolio) | C29: 250000 | E29: Liquidez inmediata · declarado en USD
B30: Activo: Pensión voluntaria (saldo) | C30: 26667 | E30: Liquidez media: según el plan de ahorro · declarado en CRC
B31: Activo: FCL (saldo) | C31: 26667 | E31: Liquidez media: cada quinquenio o al terminar la relación laboral · declarado en CRC
B32: Activo: ROP (saldo) | C32: 26667 | E32: Liquidez baja: disponible al pensionarse · declarado en CRC
B33: Activo: Inmueble: Apartamento en Santa Ana | C33: 180000 | E33: Liquidez baja: requiere su venta · declarado en USD
B34: Activo: Empresa: EMPRESA | C34: 900000 | E34: Liquidez baja: participación en una empresa · declarado en USD
B35: Activo: Capital privado (15%) | C35: 120000 | E35: Liquidez muy baja: sin mercado secundario · declarado en USD
B36: Total de activos | C36: 1530000
B37: Pasivo: Deuda: Tarjeta de crédito | C37: 3000 | E37: Corto plazo · termina en 2027 · declarado en USD
B38: Pasivo: Deuda: Préstamo personal | C38: 12000 | E38: Largo plazo · termina en 2029 · declarado en CRC
B39: Pasivo: Hipoteca de la vivienda | C39: 120000 | E39: Largo plazo · termina en 2040 · declarado en USD
B40: Total de pasivos | C40: 135000
B41: Patrimonio neto | C41: 1395000
B42: Peso del portafolio declarado por el cliente | E42: 40% del patrimonio total
B43: Peso del portafolio calculado (control) | E43: 16% de los activos declarados · no interviene en la proyección
B45: Rendimientos del plan
B46: Rendimiento mínimo esperado | C46: 0.0585725 | E46: Cartera del perfil moderado conservador
B47: Rendimiento mínimo necesario (equilibrio) | C47: 0.079180731
B48: Perfil que exige el objetivo | E48: Ninguna cartera modelo lo alcanza
B49: Holgura frente a la cartera sugerida | C49: -0.020608231
B50: Preferencia de moneda
B52: Cartera sugerida y cartera de equilibrio
B53: Clase de activo | C53: Cartera sugerida | E53: Cartera de equilibrio
B54: Renta variable | C54: 0.35 | E54: 90.0%
B55: Renta fija | C55: 0.475 | E55: 5.0%
B56: Efectivo | C56: 0.175 | E56: 5.0%
B57: Topes de la firma para el perfil | E57: Renta variable 20–35% · Renta fija 40–75% · Efectivo 5–30% · Alternativos 0–10%
B58: Ajuste de la cartera sugerida | E58: Cartera modelo ajustada a los topes del perfil moderado conservador: renta variable de 40% a 35%, renta fija de 42,5% a 47,5%.
B59: Rendimiento de la cartera de equilibrio | C59: 0.078535
B60: Volatilidad anual de la cartera de equilibrio | C60: 0.17473548
B61: Nota | E61: Ninguna combinación de carteras modelo alcanza el equilibrio; se muestra la de mayor rendimiento.
B63: Resultados de la proyección
B64: Portafolio máximo proyectado | C64: 1111058
B65: Portafolio final nominal | C65: 0
B66: Portafolio final en términos reales | C66: 0
B67: Tasa de retiro inicial | C67: 0.028085118
B68: Años de acumulación | C68: 14
B69: Años de retiro | C69: 36
B70: Edad a la que se agota el portafolio | C70: 79
B72: Caminos para alcanzar el objetivo
B73: Camino | C73: Necesario | E73: Hoy · lectura
B74: Mayor rendimiento del portafolio | C74: 7,9% | E74: Hoy 5,9% · Ninguna cartera modelo rinde lo necesario. (no basta por sí solo)
B75: Mayor capital inicial | C75: $575 034 | E75: Hoy $250 000 · Aporte único hoy de $325 034.
B76: Aporte anual adicional al portafolio | C76: $28 222 al año | E76: Durante los 14 años de acumulación, en dólares de hoy (39% del ingreso anual).
B77: Menor gasto familiar | C77: $4 643 al mes | E77: Hoy $5 500 al mes · Reducción de 16% en todos los años.
B78: Menores gastos extraordinarios | C78: — | E78: Hoy $983 474 en total · Ni eliminándolos alcanza. (no basta por sí solo)
B79: Aporte mensual adicional a la pensión voluntaria | C79: $2 172 al mes | E79: Crece al 6,0% y se recibe al pensionarse, a los 65 años.
B80: Postergar la independencia financiera | C80: 66 años | E80: Hoy 60 años · 6 años más de ingreso por actividad y de aportes.
B81: Lectura | E81: Hay 5 caminos que alcanzan el objetivo cada uno por sí solo: mayor capital inicial, aporte anual adicional al portafolio, menor gasto familiar, aporte mensual adicional a la pensión voluntaria o postergar la independencia financiera. También pueden combinarse; combinados, cada uno exige un ajuste menor.
B83: Datos financieros declarados
B84: Ingreso total mensual | C84: 2700000 | E84: CRC
B85: Gasto familiar mensual | C85: 5500 | E85: USD
B86: Capital inicial invertido | C86: 250000 | E86: USD
B87: Gasto familiar por moneda | E87: 30% en dólares · 70% en colones (cada parte con la inflación de su moneda)
B88: Comentarios del cliente
B90: Retiro, pensión, fondos y flujos previstos
B91: Gasto en el retiro (% del gasto actual) | C91: 1
B92: Régimen de pensión | E92: Magisterio Nacional
B93: Pensión mensual estimada (valor de hoy) | C93: 800000 | E93: CRC
B94: Edad de inicio de la pensión | C94: 65
B95: Otros ingresos recurrentes mensuales (valor de hoy) | C95: 500000 | E95: CRC · desde 2030 · durante toda la proyección
B96: ROP: saldo actual | C96: 12000000 | E96: CRC · pensión: retiro programado
B97: ROP: aporte mensual | E97: No lo indicó: se estima con el salario
B98: FCL: saldo actual | C98: 12000000 | E98: CRC · traslado al momento del retiro
B99: FCL: aporte mensual | E99: No lo indicó: se estima con el salario
B100: Pensión voluntaria: saldo actual | C100: 12000000 | E100: CRC · pensión mensual desde la edad de pensión
B101: Pensión voluntaria: aporte mensual | C101: 150000 | E101: CRC
B102: Ingreso extraordinario 1: Bono por antigüedad (valor de hoy) | C102: 40000 | E102: USD · año 2028
B103: Ingreso extraordinario 2: Herencia esperada (valor de hoy) | C103: 120000 | E103: USD · año 2032
B104: Desinversión: Venta del inmueble 1 | C104: 180000 | E104: USD · año 2031 · monto que entra al portafolio
B105: Desinversión: Venta de un lote | C105: 150000 | E105: USD · año 2033 · monto que entra al portafolio
B106: Gasto de dependiente 1 (valor de hoy, por año) | C106: 12000 | E106: USD · Cónyuge o pareja · salud · desde 2030 por 5 años
B107: Meta 1 (valor de hoy) | C107: 40000 | E107: USD · Vivienda o propiedad · año 2031 · deseable · salida del portafolio
B109: Perfil de permanencia y aportes
B110: Retiro: Retiro del portafolio (2031, valor de hoy) | C110: 50000 | E110: USD
B111: Destino del patrimonio | E111: Utilizarlo durante su vida
...

Sheet Proyección
B1: Proyección por flujo de caja · Cliente de ejemplo
B2: Arriba, los supuestos (columna F, con su origen en la G) y el resumen de ingresos, gastos, inversiones y desinversiones; a la derecha, el resumen del plan. Debajo, la proyección anual, toda con fórmulas. Los montos se registran, como los declaró el cliente (monto y moneda), en las hojas Ingresos, Gastos, Inversiones y Desinversiones, donde se ve el tipo de cambio aplicado y el monto en dólares; aquí solo se enlazan. Las celdas en color crema son insumos: si se cambian, toda la proyección se recalcula.
B4: Supuestos | I4: Ingresos | R4: Gastos | Z4: Inversiones y desinversiones | AG4: Resumen del plan · toda la proyección
F5: Valor | G5: Origen | L5: Valor declarado | M5: Moneda | N5: Valor usado (US$) | O5: Desde el período | P5: Hasta el período | U5: Valor declarado | V5: Moneda | W5: Valor usado (US$) | X5: Hasta el período | AC5: Valor declarado | AD5: Moneda | AE5: Valor usado (US$)
B6: Supuestos de mercado, del perfil y de la firma | I6: Ingresos ordinarios · hoja «Ingresos» | R6: Gastos ordinarios · hoja «Gastos» | Z6: Inversiones · hoja «Inversiones» | AG6: Flujo · US$ nominales | AL6: Portafolio · US$ nominales
B7: Tipo de cambio ₡/US$ | F7: 450 | G7: Asesor | I7: Ingreso total mensual (actividad) | L7: ='Ingresos'!$D$6 -> 2700000 | M7: ='Ingresos'!$E$6 -> CRC | N7: ='Ingresos'!$G$6 -> 6000 | O7: ='Ingresos'!$H$6 -> 1 | P7: ='Ingresos'!$I$6 -> 14 | R7: Gasto familiar mensual | U7: ='Gastos'!$D$6 -> 5500 | V7: ='Gastos'!$E$6 -> USD | W7: ='Gastos'!$G$6 -> 5500 | Z7: Capital inicial del portafolio | AC7: ='Inversiones'!$D$6 -> 250000 | AD7: ='Inversiones'!$E$6 -> USD | AE7: ='Inversiones'!$G$6 -> 250000 | AG7: Ingresos ordinarios | AJ7: =SUM(M30:M79) -> 5643124 | AL7: Capital inicial | AO7: =AG30 -> 250000
B8: Inflación local (Costa Rica) | F8: 0.039 | G8: Asesor | I8: Ingreso mensual de la pareja | L8: ='Ingresos'!$D$7 -> 0 | M8: ='Ingresos'!$E$7 -> USD | N8: ='Ingresos'!$G$7 -> 0 | O8: ='Ingresos'!$H$7 -> 1 | P8: ='Ingresos'!$I$7 -> 0 | R8: Gasto en el retiro (% del actual, F18) | W8: =$F$18 -> 1 | Z8: Rendimiento esperado (F13) | AE8: =$F$13 -> 0.0585725 | AG8: Ingresos extraordinarios | AJ8: =SUM(P30:P79) -> 283622 | AL8: Flujo neto (ingresos − gastos) | AO8: =SUM(AA30:AA79) -> -5563769
B9: Inflación internacional (EE. UU.) | F9: 0.039 | G9: Asesor | I9: Otros ingresos recurrentes al mes | L9: ='Ingresos'!$D$8 -> 500000 | M9: ='Ingresos'!$E$8 -> CRC | N9: ='Ingresos'!$G$8 -> 1111.11 | O9: ='Ingresos'!$H$8 -> 5 | P9: ='Ingresos'!$I$8 -> 50 | R9: Gastos de dependientes al año | W9: ='Gastos'!G18 -> 12000 | Z9: Desinversiones · hoja «Desinversiones» | AG9: Gastos ordinarios | AJ9: =-SUM(V30:V79) -> -10458610 | AL9: Flujo neto de inversiones (desinversiones) | AO9: =SUM(AF30:AF79) -> 414012
B10: Inflación de la pensión del IVM | F10: 0.01 | G10: Asesor | I10: Pensión del Magisterio (mensual) | L10: ='Pensiones'!$H$6 -> 800000 | M10: ='Pensiones'!$I$6 -> CRC | N10: ='Pensiones'!$K$6 -> 1777.78 | O10: ='Pensiones'!$L$6 -> 20 | R10: Donaciones al año | U10: ='Gastos'!$D$7 -> 3000 | V10: ='Gastos'!$E$7 -> USD | W10: ='Gastos'!$G$7 -> 3000 | Z10: Venta de inmuebles | AE10: ='Desinversiones'!G11 -> 180000 | AG10: Gastos extraordinarios | AJ10: =-SUM(Y30:Y79) -> -1031906 | AL10: Rendimientos del portafolio | AO10: =SUM(AH30:AH79) -> 1310831
B11: Inflación del ROP (aportes al ROP y al FCL) | F11: 0.039 | G11: Asesor | I11: Alquileres de inmuebles al mes | N11: ='Ingresos'!G18 -> 1100 | R11: Cuota mensual de la hipoteca | U11: ='Gastos'!$D$8 -> 1200 | V11: ='Gastos'!$E$8 -> USD | W11: ='Gastos'!$G$8 -> 1200 | X11: ='Gastos'!$I$8 -> 15 | Z11: Venta de la empresa | AE11: ='Desinversiones'!G12 -> 0 | AG11: Flujo neto | AJ11: =SUM(AA30:AA79) -> -5563769 | AL11: Gasto no cubierto por el portafolio | AO11: =SUM(AM30:AM79) -> 3588927
B12: Inflación de la pensión voluntaria | F12: 0.039 | G12: Asesor | I12: Pensión del ROP | L12: Hoja «Pensiones» | R12: Cuotas mensuales de deudas | W12: =IF('Gastos'!$G$28="Sí",0,'Gastos'!G27) -> 500 | Z12: Venta de otros activos | AE12: ='Desinversiones'!G13 -> 150000 | AG12: Resultado | AL12: Saldo final nominal | AO12: =AO7+AO8+AO9+AO10+AO11 -> 0
B13: Rendimiento esperado del portafolio | F13: 0.0585725 | G13: Perfil de riesgo | I13: Pensión voluntaria | L13: Hoja «Pensiones» | R13: Gastos extraordinarios · valor de hoy | AG13: Herencia deseada (US$ de hoy) | AJ13: 0 | AL13: Saldo final en dólares de hoy | AO13: =AK79 -> 0
B14: Rendimiento de los fondos de pensión | F14: 0.06 | G14: Asesor | I14: Ingresos extraordinarios · valor de hoy | R14: Gastos extraordinarios | W14: ='Gastos'!G38 -> 41000 | AG14: Edad a la que se agota el portafolio | AJ14: =IF(AO14>0,SUMPRODUCT(MIN((AM30:AM79>0)*C30:C79+(AM30:AM79<=0)*1000)),"No se agota") -> 79 | AL14: Gasto no cubierto, en dólares de hoy | AO14: =SUMPRODUCT(AM30:AM79/(1+$F$9)^D30:D79) -> 689048
B15: Aporte al ROP (% del salario, si se estima) | F15: 0.0425 | G15: Asesor | I15: Ingresos extraordinarios | N15: ='Ingresos'!G27 -> 160000 | R15: Retiros adicionales del portafolio | W15: ='Retiros del portafolio'!G19 -> 50000 | AG15: ¿Alcanza el plan? | AJ15: =IF(AND(AO14<=0,AO13>=AJ13),"Sí alcanza","No alcanza") -> No alcanza | AL15: Saldo del ROP al final (fuera del portafolio) | AO15: ='Pensiones'!H68 -> 52882
B16: Aporte al FCL (% del salario, si se estima) | F16: 0.015 | G16: Asesor | I16: Traslado del FCL | L16: Hoja «Pensiones» | R16: Metas pagadas con el portafolio | W16: ='Retiros del portafolio'!G10 -> 40000
B17: Datos del cliente
B18: Gasto en el retiro (% del gasto actual) | F18: 1 | G18: Cuestionario
B19: Años hasta la independencia | F19: 14 | G19: Cuestionario
B20: Edad de inicio de la pensión | F20: 65 | G20: Cuestionario
B21: Mes de nacimiento (1 a 12) | F21: 5 | G21: Cuestionario
B22: Gasto familiar pagado en dólares (%) | F22: 0.3 | G22: Cuestionario
B23: Gasto familiar pagado en colones (%) | F23: =1-$F$22 -> 0.7 | G23: El resto
B24: Meses del primer año (1 a 12) | F24: 3 | G24: Fecha del cuestionario
B27: Proyección anual · dólares nominales
B28: Período | F28: Ingresos ordinarios | N28: Ingresos extraordinarios | Q28: Ingresos totales | R28: Gastos ordinarios | W28: Gastos extraordinarios | Z28: Gastos totales | AA28: Flujo neto | AB28: Desinversiones | AF28: Flujo neto de inversiones | AG28: Portafolio
B29: Año | C29: Edad | D29: Período | E29: Fase | F29: Ingreso total (actividad) | G29: Ingreso de la pareja | H29: Otros ingresos recurrentes | I29: Alquileres de inmuebles | J29: Pensión del Magisterio | K29: Pensión del ROP | L29: Pensión voluntaria | M29: Total ingresos ordinarios | N29: Ingresos extraordinarios | O29: Traslado del FCL | P29: Total ingresos extraordinarios | Q29: Total ingresos | R29: Gasto familiar | S29: Gastos de dependientes | T29: Donaciones | U29: Cuotas de hipoteca y deudas | V29: Total gastos ordinarios | W29: Gastos extraordinarios | X29: Inversiones | Y29: Total salidas | Z29: Total gastos | AA29: Flujo neto (ingresos − gastos) | AB29: Venta de inmuebles | AC29: Venta de la empresa | AD29: Venta de otros activos | AE29: Total desinversiones | AF29: Flujo neto de inversiones (desinversiones) | AG29: Portafolio inicial | AH29: Rendimiento | AI29: Flujo neto | AJ29: Portafolio final nominal | AK29: Portafolio en términos reales | AL29: Tasa de retiro (% del portafolio) | AM29: Gasto no cubierto
B30: 2026 | C30: 46 | D30: 1 | E30: =IF(D30<=$F$19,"Acumulación","Retiro") -> Acumulación | F30: =IF(D30<=$P$7,$N$7*12*(1+IF($M$7="CRC",N($F$8),$F$9))^(D30-1),0)*$F$24/12 -> 18000 | G30: =IF(D30<=$P$8,$N$8*12*(1+IF($M$8="CRC",N($F$8),$F$9))^(D30-1),0)*$F$24/12 -> 0 | H30: =IF(AND($N$9>0,D30>=$O$9,D30<=$P$9),$N$9*12*(1+IF($M$9="CRC",N($F$8),$F$9))^(D30-1),0)*$F$24/12 -> 0 | I30: =SUMPRODUCT(('Ingresos'!$H$14:$H$17>=B30)*'Ingresos'!$G$14:$G$17*(1+('Ingresos'!$E$14:$E$17="CRC")*N($F$8)+('Ingresos'!$E$14:$E$17<>"CRC")*$F$9)^(D30-1))*12*$F$24/12 -> 3300 | J30: =IF(AND($N$10>0,D30>=N($O$10)),$N$10*12*(1+IF($M$10="CRC",N($F$8),$F$9))^(N($O$10)-1)*(1+N($F$10))^(D30-N($O$10))*MIN(IF(D30=N($O$10),IF(AND(ISNUMBER($F$21),N($F$20)>=$C$30),(12-$F$21)/12,1),1),$F$24/12),0) -> 0 | K30: ='Pensiones'!T19 -> 0 | L30: ='Pensiones'!U19 -> 0 | M30: =SUM(F30:L30) -> 21300 | N30: =SUMPRODUCT(('Ingresos'!$H$22:$H$26=B30)*'Ingresos'!$G$22:$G$26*(1+('Ingresos'!$E$22:$E$26="CRC")*N($F$8)+('Ingresos'!$E$22:$E$26<>"CRC")*$F$9)^(D30-1)) -> 0 | O30: ='Pensiones'!S19 -> 0 | P30: =SUM(N30:O30) -> 0 | Q30: =M30+P30 -> 21300 | R30: =$W$7*12*(N($F$22)*(1+$F$9)^(D30-1)+(1-N($F$22))*(1+N($F$8))^(D30-1))*IF(D30>$F$19,$F$18,1)*$F$24/12 -> 16500 | S30: =SUMPRODUCT(('Gastos'!$H$14:$H$17<=B30)*('Gastos'!$H$14:$H$17+'Gastos'!$I$14:$I$17>B30)*'Gastos'!$G$14:$G$17*(1+('Gastos'!$E$14:$E$17="CRC")*N($F$8)+('Gastos'!$E$14:$E$17<>"CRC")*$F$9)^(D30-1))*$F$24/12 -> 0 | T30: =$W$10*(1+IF($V$10="CRC",N($F$8),$F$9))^(D30-1)*$F$24/12 -> 750 | U30: =(IF(D30<=$X$11,$W$11*12,0)+IF('Gastos'!$G$28="Sí",0,SUMPRODUCT(('Gastos'!$H$22:$H$26>=B30)*'Gastos'!$G$22:$G$26)*12)+SUMPRODUCT(('Gastos'!$H$43:$H$45<=B30)*('Gastos'!$H$43:$H$45+'Gastos'!$I$43:$I$45-1>=B30)*'Gastos'!$K$43:$K$45))*$F$24/12 -> 5100 | V30: =SUM(R30:U30) -> 22350 | W30: =SUMPRODUCT(('Gastos'!$I$33:$I$37=1)*('Gastos'!$H$33:$H$37=B30)*'Gastos'!$G$33:$G$37*(1+('Gastos'!$E$33:$E$37="CRC")*N($F$8)+('Gastos'!$E$33:$E$37<>"CRC")*$F$9)^(D30-1))+SUMPRODUCT(('Gastos'!$I$33:$I$37=2)*('Gastos'!$H$33:$H$37<=B30)*'Gastos'!$G$33:$G$37*(1+('Gastos'!$E$33:$E$37="CRC")*N($F$8)+('Gastos'!$E$33:$E$37<>"CRC")*$F$9)^(D30-1))*$F$24/12+SUMPRODUCT(('Retiros del portafolio'!$H$15:$H$18=B30)*'Retiros del portafolio'!$G$15:$G$18*(1+('Retiros del portafolio'!$E$15:$E$18="CRC")*N($F$8)+('Retiros del portafolio'!$E$15:$E$18<>"CRC")*$F$9)^(D30-1)) -> 0 | X30: =SUMPRODUCT(('Retiros del portafolio'!$H$6:$H$9=B30)*'Retiros del portafolio'!$G$6:$G$9*(1+('Retiros del portafolio'!$E$6:$E$9="CRC")*N($F$8)+('Retiros del portafolio'!$E$6:$E$9<>"CRC")*$F$9)^(D30-1)) -> 0 | Y30: =W30+X30 -> 0 | Z30: =V30+Y30 -> 22350 | AA30: =Q30-Z30 -> -1050 | AB30: =SUMPRODUCT(('Desinversiones'!$H$6:$H$10=B30)*('Desinversiones'!$I$6:$I$10=1)*'Desinversiones'!$G$6:$G$10*(1+('Desinversiones'!$E$6:$E$10="CRC")*N($F$8)+('Desinversiones'!$E$6:$E$10<>"CRC")*$F$9)^(D30-1)) -> 0 | AC30: =SUMPRODUCT(('Desinversiones'!$H$6:$H$10=B30)*('Desinversiones'!$I$6:$I$10=2)*'Desinversiones'!$G$6:$G$10*(1+('Desinversiones'!$E$6:$E$10="CRC")*N($F$8)+('Desinversiones'!$E$6:$E$10<>"CRC")*$F$9)^(D30-1)) -> 0 | AD30: =SUMPRODUCT(('Desinversiones'!$H$6:$H$10=B30)*('Desinversiones'!$I$6:$I$10=3)*'Desinversiones'!$G$6:$G$10*(1+('Desinversiones'!$E$6:$E$10="CRC")*N($F$8)+('Desinversiones'!$E$6:$E$10<>"CRC")*$F$9)^(D30-1)) -> 0 | AE30: =SUM(AB30:AD30) -> 0 | AF30: =AE30 -> 0 | AG30: =$AE$7 -> 250000 | AH30: =AG30*$F$13*$F$24/12 -> 3661 | AI30: =AA30+AF30 -> -1050 | AJ30: =AG30+AH30+AI30+AM30 -> 252611 | AK30: =AJ30/(1+$F$9)^(D30-1+$F$24/12) -> 250206 | AL30: =IF(AG30<=0,0,MAX(0,-AI30)/AG30) -> 0.0042 | AM30: =MAX(0,-(AG30+AH30+AI30)) -> 0
B31: =B30+1 -> 2027 | C31: =C30+1 -> 47 | D31: =D30+1 -> 2 | E31: =IF(D31<=$F$19,"Acumulación","Retiro") -> Acumulación | F31: =IF(D31<=$P$7,$N$7*12*(1+IF($M$7="CRC",N($F$8),$F$9))^(D31-1),0) -> 74808 | G31: =IF(D31<=$P$8,$N$8*12*(1+IF($M$8="CRC",N($F$8),$F$9))^(D31-1),0) -> 0 | H31: =IF(AND($N$9>0,D31>=$O$9,D31<=$P$9),$N$9*12*(1+IF($M$9="CRC",N($F$8),$F$9))^(D31-1),0) -> 0 | I31: =SUMPRODUCT(('Ingresos'!$H$14:$H$17>=B31)*'Ingresos'!$G$14:$G$17*(1+('Ingresos'!$E$14:$E$17="CRC")*N($F$8)+('Ingresos'!$E$14:$E$17<>"CRC")*$F$9)^(D31-1))*12 -> 13715 | J31: =IF(AND($N$10>0,D31>=N($O$10)),$N$10*12*(1+IF($M$10="CRC",N($F$8),$F$9))^(N($O$10)-1)*(1+N($F$10))^(D31-N($O$10))*IF(D31=N($O$10),IF(AND(ISNUMBER($F$21),N($F$20)>=$C$30),(12-$F$21)/12,1),1),0) -> 0 | K31: ='Pensiones'!T20 -> 0 | L31: ='Pensiones'!U20 -> 0 | M31: =SUM(F31:L31) -> 88523 | N31: =SUMPRODUCT(('Ingresos'!$H$22:$H$26=B31)*'Ingresos'!$G$22:$G$26*(1+('Ingresos'!$E$22:$E$26="CRC")*N($F$8)+('Ingresos'!$E$22:$E$26<>"CRC")*$F$9)^(D31-1)) -> 0 | O31: ='Pensiones'!S20 -> 0 | P31: =SUM(N31:O31) -> 0 | Q31: =M31+P31 -> 88523 | R31: =$W$7*12*(N($F$22)*(1+$F$9)^(D31-1)+(1-N($F$22))*(1+N($F$8))^(D31-1))*IF(D31>$F$19,$F$18,1) -> 68574 | S31: =SUMPRODUCT(('Gastos'!$H$14:$H$17<=B31)*('Gastos'!$H$14:$H$17+'Gastos'!$I$14:$I$17>B31)*'Gastos'!$G$14:$G$17*(1+('Gastos'!$E$14:$E$17="CRC")*N($F$8)+('Gastos'!$E$14:$E$17<>"CRC")*$F$9)^(D31-1)) -> 0 | T31: =$W$10*(1+IF($V$10="CRC",N($F$8),$F$9))^(D31-1) -> 3117 | U31: =(IF(D31<=$X$11,$W$11*12,0)+IF('Gastos'!$G$28="Sí",0,SUMPRODUCT(('Gastos'!$H$22:$H$26>=B31)*'Gastos'!$G$22:$G$26)*12)+SUMPRODUCT(('Gastos'!$H$43:$H$45<=B31)*('Gastos'!$H$43:$H$45+'Gastos'!$I$43:$I$45-1>=B31)*'Gastos'!$K$43:$K$45)) -> 20400 | V31: =SUM(R31:U31) -> 92091 | W31: =SUMPRODUCT(('Gastos'!$I$33:$I$37=1)*('Gastos'!$H$33:$H$37=B31)*'Gastos'!$G$33:$G$37*(1+('Gastos'!$E$33:$E$37="CRC")*N($F$8)+('Gastos'!$E$33:$E$37<>"CRC")*$F$9)^(D31-1))+SUMPRODUCT(('Gastos'!$I$33:$I$37=2)*('Gastos'!$H$33:$H$37<=B31)*'Gastos'!$G$33:$G$37*(1+('Gastos'!$E$33:$E$37="CRC")*N($F$8)+('Gastos'!$E$33:$E$37<>"CRC")*$F$9)^(D31-1))+SUMPRODUCT(('Retiros del portafolio'!$H$15:$H$18=B31)*'Retiros del portafolio'!$G$15:$G$18*(1+('Retiros del portafolio'!$E$15:$E$18="CRC")*N($F$8)+('Retiros del portafolio'!$E$15:$E$18<>"CRC")*$F$9)^(D31-1)) -> 6234 | X31: =SUMPRODUCT(('Retiros del portafolio'!$H$6:$H$9=B31)*'Retiros del portafolio'!$G$6:$G$9*(1+('Retiros del portafolio'!$E$6:$E$9="CRC")*N($F$8)+('Retiros del portafolio'!$E$6:$E$9<>"CRC")*$F$9)^(D31-1)) -> 0 | Y31: =W31+X31 -> 6234 | Z31: =V31+Y31 -> 98325 | AA31: =Q31-Z31 -> -9802 | AB31: =SUMPRODUCT(('Desinversiones'!$H$6:$H$10=B31)*('Desinversiones'!$I$6:$I$10=1)*'Desinversiones'!$G$6:$G$10*(1+('Desinversiones'!$E$6:$E$10="CRC")*N($F$8)+('Desinversiones'!$E$6:$E$10<>"CRC")*$F$9)^(D31-1)) -> 0 | AC31: =SUMPRODUCT(('Desinversiones'!$H$6:$H$10=B31)*('Desinversiones'!$I$6:$I$10=2)*'Desinversiones'!$G$6:$G$10*(1+('Desinversiones'!$E$6:$E$10="CRC")*N($F$8)+('Desinversiones'!$E$6:$E$10<>"CRC")*$F$9)^(D31-1)) -> 0 | AD31: =SUMPRODUCT(('Desinversiones'!$H$6:$H$10=B31)*('Desinversiones'!$I$6:$I$10=3)*'Desinversiones'!$G$6:$G$10*(1+('Desinversiones'!$E$6:$E$10="CRC")*N($F$8)+('Desinversiones'!$E$6:$E$10<>"CRC")*$F$9)^(D31-1)) -> 0 | AE31: =SUM(AB31:AD31) -> 0 | AF31: =AE31 -> 0 | AG31: =AJ30 -> 252611 | AH31: =AG31*$F$13 -> 14796 | AI31: =AA31+AF31 -> -9802 | AJ31: =AG31+AH31+AI31+AM31 -> 257605 | AK31: =AJ31/(1+$F$9)^(D31-1+$F$24/12) -> 245575 | AL31: =IF(AG31<=0,0,MAX(0,-AI31)/AG31) -> 0.038803569 | AM31: =MAX(0,-(AG31+AH31+AI31)) -> 0
B32: =B31+1 -> 2028 | C32: =C31+1 -> 48 | D32: =D31+1 -> 3 | E32: =IF(D32<=$F$19,"Acumulación","Retiro") -> Acumulación | F32: =IF(D32<=$P$7,$N$7*12*(1+IF($M$7="CRC",N($F$8),$F$9))^(D32-1),0) -> 77726 | G32: =IF(D32<=$P$8,$N$8*12*(1+IF($M$8="CRC",N($F$8),$F$9))^(D32-1),0) -> 0 | H32: =IF(AND($N$9>0,D32>=$O$9,D32<=$P$9),$N$9*12*(1+IF($M$9="CRC",N($F$8),$F$9))^(D32-1),0) -> 0 | I32: =SUMPRODUCT(('Ingresos'!$H$14:$H$17>=B32)*'Ingresos'!$G$14:$G$17*(1+('Ingresos'!$E$14:$E$17="CRC")*N($F$8)+('Ingresos'!$E$14:$E$17<>"CRC")*$F$9)^(D32-1))*12 -> 14250 | J32: =IF(AND($N$10>0,D32>=N($O$10)),$N$10*12*(1+IF($M$10="CRC",N($F$8),$F$9))^(N($O$10)-1)*(1+N($F$10))^(D32-N($O$10))*IF(D32=N($O$10),IF(AND(ISNUMBER($F$21),N($F$20)>=$C$30),(12-$F$21)/12,1),1),0) -> 0 | K32: ='Pensiones'!T21 -> 0 | L32: ='Pensiones'!U21 -> 0 | M32: =SUM(F32:L32) -> 91975 | N32: =SUMPRODUCT(('Ingresos'!$H$22:$H$26=B32)*'Ingresos'!$G$22:$G$26*(1+('Ingresos'!$E$22:$E$26="CRC")*N($F$8)+('Ingresos'!$E$22:$E$26<>"CRC")*$F$9)^(D32-1)) -> 43181 | O32: ='Pensiones'!S21 -> 0 | P32: =SUM(N32:O32) -> 43181 | Q32: =M32+P32 -> 135156 | R32: =$W$7*12*(N($F$22)*(1+$F$9)^(D32-1)+(1-N($F$22))*(1+N($F$8))^(D32-1))*IF(D32>$F$19,$F$18,1) -> 71248 | S32: =SUMPRODUCT(('Gastos'!$H$14:$H$17<=B32)*('Gastos'!$H$14:$H$17+'Gastos'!$I$14:$I$17>B32)*'Gastos'!$G$14:$G$17*(1+('Gastos'!$E$14:$E$17="CRC")*N($F$8)+('Gastos'!$E$14:$E$17<>"CRC")*$F$9)^(D32-1)) -> 0 | T32: =$W$10*(1+IF($V$10="CRC",N($F$8),$F$9))^(D32-1) -> 3239 | U32: =(IF(D32<=$X$11,$W$11*12,0)+IF('Gastos'!$G$28="Sí",0,SUMPRODUCT(('Gastos'!$H$22:$H$26>=B32)*'Gastos'!$G$22:$G$26)*12)+SUMPRODUCT(('Gastos'!$H$43:$H$45<=B32)*('Gastos'!$H$43:$H$45+'Gastos'!$I$43:$I$45-1>=B32)*'Gastos'!$K$43:$K$45)) -> 18600 | V32: =SUM(R32:U32) -> 93087 | W32: =SUMPRODUCT(('Gastos'!$I$33:$I$37=1)*('Gastos'!$H$33:$H$37=B32)*'Gastos'!$G$33:$G$37*(1+('Gastos'!$E$33:$E$37="CRC")*N($F$8)+('Gastos'!$E$33:$E$37<>"CRC")*$F$9)^(D32-1))+SUMPRODUCT(('Gastos'!$I$33:$I$37=2)*('Gastos'!$H$33:$H$37<=B32)*'Gastos'!$G$33:$G$37*(1+('Gastos'!$E$33:$E$37="CRC")*N($F$8)+('Gastos'!$E$33:$E$37<>"CRC")*$F$9)^(D32-1))+SUMPRODUCT(('Retiros del portafolio'!$H$15:$H$18=B32)*'Retiros del portafolio'!$G$15:$G$18*(1+('Retiros del portafolio'!$E$15:$E$18="CRC")*N($F$8)+('Retiros del portafolio'!$E$15:$E$18<>"CRC")*$F$9)^(D32-1)) -> 6477 | X32: =SUMPRODUCT(('Retiros del portafolio'!$H$6:$H$9=B32)*'Retiros del portafolio'!$G$6:$G$9*(1+('Retiros del portafolio'!$E$6:$E$9="CRC")*N($F$8)+('Retiros del portafolio'!$E$6:$E$9<>"CRC")*$F$9)^(D32-1)) -> 0 | Y32: =W32+X32 -> 6477 | Z32: =V32+Y32 -> 99564 | AA32: =Q32-Z32 -> 35592 | AB32: =SUMPRODUCT(('Desinversiones'!$H$6:$H$10=B32)*('Desinversiones'!$I$6:$I$10=1)*'Desinversiones'!$G$6:$G$10*(1+('Desinversiones'!$E$6:$E$10="CRC")*N($F$8)+('Desinversiones'!$E$6:$E$10<>"CRC")*$F$9)^(D32-1)) -> 0 | AC32: =SUMPRODUCT(('Desinversiones'!$H$6:$H$10=B32)*('Desinversiones'!$I$6:$I$10=2)*'Desinversiones'!$G$6:$G$10*(1+('Desinversiones'!$E$6:$E$10="CRC")*N($F$8)+('Desinversiones'!$E$6:$E$10<>"CRC")*$F$9)^(D32-1)) -> 0 | AD32: =SUMPRODUCT(('Desinversiones'!$H$6:$H$10=B32)*('Desinversiones'!$I$6:$I$10=3)*'Desinversiones'!$G$6:$G$10*(1+('Desinversiones'!$E$6:$E$10="CRC")*N($F$8)+('Desinversiones'!$E$6:$E$10<>"CRC")*$F$9)^(D32-1)) -> 0 | AE32: =SUM(AB32:AD32) -> 0 | AF32: =AE32 -> 0 | AG32: =AJ31 -> 257605 | AH32: =AG32*$F$13 -> 15089 | AI32: =AA32+AF32 -> 35592 | AJ32: =AG32+AH32+AI32+AM32 -> 308285 | AK32: =AJ32/(1+$F$9)^(D32-1+$F$24/12) -> 282857 | AL32: =IF(AG32<=0,0,MAX(0,-AI32)/AG32) -> 0 | AM32: =MAX(0,-(AG32+AH32+AI32)) -> 0
B33: =B32+1 -> 2029 | C33: =C32+1 -> 49 | D33: =D32+1 -> 4 | E33: =IF(D33<=$F$19,"Acumulación","Retiro") -> Acumulación | F33: =IF(D33<=$P$7,$N$7*12*(1+IF($M$7="CRC",N($F$8),$F$9))^(D33-1),0) -> 80757 | G33: =IF(D33<=$P$8,$N$8*12*(1+IF($M$8="CRC",N($F$8),$F$9))^(D33-1),0) -> 0 | H33: =IF(AND($N$9>0,D33>=$O$9,D33<=$P$9),$N$9*12*(1+IF($M$9="CRC",N($F$8),$F$9))^(D33-1),0) -> 0 | I33: =SUMPRODUCT(('Ingresos'!$H$14:$H$17>=B33)*'Ingresos'!$G$14:$G$17*(1+('Ingresos'!$E$14:$E$17="CRC")*N($F$8)+('Ingresos'!$E$14:$E$17<>"CRC")*$F$9)^(D33-1))*12 -> 14805 | J33: =IF(AND($N$10>0,D33>=N($O$10)),$N$10*12*(1+IF($M$10="CRC",N($F$8),$F$9))^(N($O$10)-1)*(1+N($F$10))^(D33-N($O$10))*IF(D33=N($O$10),IF(AND(ISNUMBER($F$21),N($F$20)>=$C$30),(12-$F$21)/12,1),1),0) -> 0 | K33: ='Pensiones'!T22 -> 0 | L33: ='Pensiones'!U22 -> 0 | M33: =SUM(F33:L33) -> 95562 | N33: =SUMPRODUCT(('Ingresos'!$H$22:$H$26=B33)*'Ingresos'!$G$22:$G$26*(1+('Ingresos'!$E$22:$E$26="CRC")*N($F$8)+('Ingresos'!$E$22:$E$26<>"CRC")*$F$9)^(D33-1)) -> 0 | O33: ='Pensiones'!S22 -> 0 | P33: =SUM(N33:O33) -> 0 | Q33: =M33+P33 -> 95562 | R33: =$W$7*12*(N($F$22)*(1+$F$9)^(D33-1)+(1-N($F$22))*(1+N($F$8))^(D33-1))*IF(D33>$F$19,$F$18,1) -> 74027 | S33: =SUMPRODUCT(('Gastos'!$H$14:$H$17<=B33)*('Gastos'!$H$14:$H$17+'Gastos'!$I$14:$I$17>B33)*'Gastos'!$G$14:$G$17*(1+('Gastos'!$E$14:$E$17="CRC")*N($F$8)+('Gastos'!$E$14:$E$17<>"CRC")*$F$9)^(D33-1)) -> 0 | T33: =$W$10*(1+IF($V$10="CRC",N($F$8),$F$9))^(D33-1) -> 3365 | U33: =(IF(D33<=$X$11,$W$11*12,0)+IF('Gastos'!$G$28="Sí",0,SUMPRODUCT(('Gastos'!$H$22:$H$26>=B33)*'Gastos'!$G$22:$G$26)*12)+SUMPRODUCT(('Gastos'!$H$43:$H$45<=B33)*('Gastos'!$H$43:$H$45+'Gastos'!$I$43:$I$45-1>=B33)*'Gastos'!$K$43:$K$45)) -> 18600 | V33: =SUM(R33:U33) -> 95992 | W33: =SUMPRODUCT(('Gastos'!$I$33:$I$37=1)*('Gastos'!$H$33:$H$37=B33)*'Gastos'!$G$33:$G$37*(1+('Gastos'!$E$33:$E$37="CRC")*N($F$8)+('Gastos'!$E$33:$E$37<>"CRC")*$F$9)^(D33-1))+SUMPRODUCT(('Gastos'!$I$33:$I$37=2)*('Gastos'!$H$33:$H$37<=B33)*'Gastos'!$G$33:$G$37*(1+('Gastos'!$E$33:$E$37="CRC")*N($F$8)+('Gastos'!$E$33:$E$37<>"CRC")*$F$9)^(D33-1))+SUMPRODUCT(('Retiros del portafolio'!$H$15:$H$18=B33)*'Retiros del portafolio'!$G$15:$G$18*(1+('Retiros del portafolio'!$E$15:$E$18="CRC")*N($F$8)+('Retiros del portafolio'!$E$15:$E$18<>"CRC")*$F$9)^(D33-1)) -> 6730 | X33: =SUMPRODUCT(('Retiros del portafolio'!$H$6:$H$9=B33)*'Retiros del portafolio'!$G$6:$G$9*(1+('Retiros del portafolio'!$E$6:$E$9="CRC")*N($F$8)+('Retiros del portafolio'!$E$6:$E$9<>"CRC")*$F$9)^(D33-1)) -> 0 | Y33: =W33+X33 -> 6730 | Z33: =V33+Y33 -> 102722 | AA33: =Q33-Z33 -> -7159 | AB33: =SUMPRODUCT(('Desinversiones'!$H$6:$H$10=B33)*('Desinversiones'!$I$6:$I$10=1)*'Desinversiones'!$G$6:$G$10*(1+('Desinversiones'!$E$6:$E$10="CRC")*N($F$8)+('Desinversiones'!$E$6:$E$10<>"CRC")*$F$9)^(D33-1)) -> 0 | AC33: =SUMPRODUCT(('Desinversiones'!$H$6:$H$10=B33)*('Desinversiones'!$I$6:$I$10=2)*'Desinversiones'!$G$6:$G$10*(1+('Desinversiones'!$E$6:$E$10="CRC")*N($F$8)+('Desinversiones'!$E$6:$E$10<>"CRC")*$F$9)^(D33-1)) -> 0 | AD33: =SUMPRODUCT(('Desinversiones'!$H$6:$H$10=B33)*('Desinversiones'!$I$6:$I$10=3)*'Desinversiones'!$G$6:$G$10*(1+('Desinversiones'!$E$6:$E$10="CRC")*N($F$8)+('Desinversiones'!$E$6:$E$10<>"CRC")*$F$9)^(D33-1)) -> 0 | AE33: =SUM(AB33:AD33) -> 0 | AF33: =AE33 -> 0 | AG33: =AJ32 -> 308285 | AH33: =AG33*$F$13 -> 18057 | AI33: =AA33+AF33 -> -7159 | AJ33: =AG33+AH33+AI33+AM33 -> 319183 | AK33: =AJ33/(1+$F$9)^(D33-1+$F$24/12) -> 281863 | AL33: =IF(AG33<=0,0,MAX(0,-AI33)/AG33) -> 0.023223476 | AM33: =MAX(0,-(AG33+AH33+AI33)) -> 0
B34: =B33+1 -> 2030 | C34: =C33+1 -> 50 | D34: =D33+1 -> 5 | E34: =IF(D34<=$F$19,"Acumulación","Retiro") -> Acumulación | F34: =IF(D34<=$P$7,$N$7*12*(1+IF($M$7="CRC",N($F$8),$F$9))^(D34-1),0) -> 83906 | G34: =IF(D34<=$P$8,$N$8*12*(1+IF($M$8="CRC",N($F$8),$F$9))^(D34-1),0) -> 0 | H34: =IF(AND($N$9>0,D34>=$O$9,D34<=$P$9),$N$9*12*(1+IF($M$9="CRC",N($F$8),$F$9))^(D34-1),0) -> 15538 | I34: =SUMPRODUCT(('Ingresos'!$H$14:$H$17>=B34)*'Ingresos'!$G$14:$G$17*(1+('Ingresos'!$E$14:$E$17="CRC")*N($F$8)+('Ingresos'!$E$14:$E$17<>"CRC")*$F$9)^(D34-1))*12 -> 15383 | J34: =IF(AND($N$10>0,D34>=N($O$10)),$N$10*12*(1+IF($M$10="CRC",N($F$8),$F$9))^(N($O$10)-1)*(1+N($F$10))^(D34-N($O$10))*IF(D34=N($O$10),IF(AND(ISNUMBER($F$21),N($F$20)>=$C$30),(12-$F$21)/12,1),1),0) -> 0 | K34: ='Pensiones'!T23 -> 0 | L34: ='Pensiones'!U23 -> 0 | M34: =SUM(F34:L34) -> 114827 | N34: =SUMPRODUCT(('Ingresos'!$H$22:$H$26=B34)*'Ingresos'!$G$22:$G$26*(1+('Ingresos'!$E$22:$E$26="CRC")*N($F$8)+('Ingresos'!$E$22:$E$26<>"CRC")*$F$9)^(D34-1)) -> 0 | O34: ='Pensiones'!S23 -> 0 | P34: =SUM(N34:O34) -> 0 | Q34: =M34+P34 -> 114827 | R34: =$W$7*12*(N($F$22)*(1+$F$9)^(D34-1)+(1-N($F$22))*(1+N($F$8))^(D34-1))*IF(D34>$F$19,$F$18,1) -> 76914 | S34: =SUMPRODUCT(('Gastos'!$H$14:$H$17<=B34)*('Gastos'!$H$14:$H$17+'Gastos'!$I$14:$I$17>B34)*'Gastos'!$G$14:$G$17*(1+('Gastos'!$E$14:$E$17="CRC")*N($F$8)+('Gastos'!$E$14:$E$17<>"CRC")*$F$9)^(D34-1)) -> 13984 | T34: =$W$10*(1+IF($V$10="CRC",N($F$8),$F$9))^(D34-1) -> 3496 | U34: =(IF(D34<=$X$11,$W$11*12,0)+IF('Gastos'!$G$28="Sí",0,SUMPRODUCT(('Gastos'!$H$22:$H$26>=B34)*'Gastos'!$G$22:$G$26)*12)+SUMPRODUCT(('Gastos'!$H$43:$H$45<=B34)*('Gastos'!$H$43:$H$45+'Gastos'!$I$43:$I$45-1>=B34)*'Gastos'!$K$43:$K$45)) -> 14400 | V34: =SUM(R34:U34) -> 108795 | W34: =SUMPRODUCT(('Gastos'!$I$33:$I$37=1)*('Gastos'!$H$33:$H$37=B34)*'Gastos'!$G$33:$G$37*(1+('Gastos'!$E$33:$E$37="CRC")*N($F$8)+('Gastos'!$E$33:$E$37<>"CRC")*$F$9)^(D34-1))+SUMPRODUCT(('Gastos'!$I$33:$I$37=2)*('Gastos'!$H$33:$H$37<=B34)*'Gastos'!$G$33:$G$37*(1+('Gastos'!$E$33:$E$37="CRC")*N($F$8)+('Gastos'!$E$33:$E$37<>"CRC")*$F$9)^(D34-1))+SUMPRODUCT(('Retiros del portafolio'!$H$15:$H$18=B34)*'Retiros del portafolio'!$G$15:$G$18*(1+('Retiros del portafolio'!$E$15:$E$18="CRC")*N($F$8)+('Retiros del portafolio'!$E$15:$E$18<>"CRC")*$F$9)^(D34-1)) -> 47780 | X34: =SUMPRODUCT(('Retiros del portafolio'!$H$6:$H$9=B34)*'Retiros del portafolio'!$G$6:$G$9*(1+('Retiros del portafolio'!$E$6:$E$9="CRC")*N($F$8)+('Retiros del portafolio'!$E$6:$E$9<>"CRC")*$F$9)^(D34-1)) -> 0 | Y34: =W34+X34 -> 47780 | Z34: =V34+Y34 -> 156575 | AA34: =Q34-Z34 -> -41747 | AB34: =SUMPRODUCT(('Desinversiones'!$H$6:$H$10=B34)*('Desinversiones'!$I$6:$I$10=1)*'Desinversiones'!$G$6:$G$10*(1+('Desinversiones'!$E$6:$E$10="CRC")*N($F$8)+('Desinversiones'!$E$6:$E$10<>"CRC")*$F$9)^(D34-1)) -> 0 | AC34: =SUMPRODUCT(('Desinversiones'!$H$6:$H$10=B34)*('Desinversiones'!$I$6:$I$10=2)*'Desinversiones'!$G$6:$G$10*(1+('Desinversiones'!$E$6:$E$10="CRC")*N($F$8)+('Desinversiones'!$E$6:$E$10<>"CRC")*$F$9)^(D34-1)) -> 0 | AD34: =SUMPRODUCT(('Desinversiones'!$H$6:$H$10=B34)*('Desinversiones'!$I$6:$I$10=3)*'Desinversiones'!$G$6:$G$10*(1+('Desinversiones'!$E$6:$E$10="CRC")*N($F$8)+('Desinversiones'!$E$6:$E$10<>"CRC")*$F$9)^(D34-1)) -> 0 | AE34: =SUM(AB34:AD34) -> 0 | AF34: =AE34 -> 0 | AG34: =AJ33 -> 319183 | AH34: =AG34*$F$13 -> 18695 | AI34: =AA34+AF34 -> -41747 | AJ34: =AG34+AH34+AI34+AM34 -> 296131 | AK34: =AJ34/(1+$F$9)^(D34-1+$F$24/12) -> 251691 | AL34: =IF(AG34<=0,0,MAX(0,-AI34)/AG34) -> 0.1307942 | AM34: =MAX(0,-(AG34+AH34+AI34)) -> 0
B35: =B34+1 -> 2031 | C35: =C34+1 -> 51 | D35: =D34+1 -> 6 | E35: =IF(D35<=$F$19,"Acumulación","Retiro") -> Acumulación | F35: =IF(D35<=$P$7,$N$7*12*(1+IF($M$7="CRC",N($F$8),$F$9))^(D35-1),0) -> 87179 | G35: =IF(D35<=$P$8,$N$8*12*(1+IF($M$8="CRC",N($F$8),$F$9))^(D35-1),0) -> 0 | H35: =IF(AND($N$9>0,D35>=$O$9,D35<=$P$9),$N$9*12*(1+IF($M$9="CRC",N($F$8),$F$9))^(D35-1),0) -> 16144 | I35: =SUMPRODUCT(('Ingresos'!$H$14:$H$17>=B35)*'Ingresos'!$G$14:$G$17*(1+('Ingresos'!$E$14:$E$17="CRC")*N($F$8)+('Ingresos'!$E$14:$E$17<>"CRC")*$F$9)^(D35-1))*12 -> 0 | J35: =IF(AND($N$10>0,D35>=N($O$10)),$N$10*12*(1+IF($M$10="CRC",N($F$8),$F$9))^(N($O$10)-1)*(1+N($F$10))^(D35-N($O$10))*IF(D35=N($O$10),IF(AND(ISNUMBER($F$21),N($F$20)>=$C$30),(12-$F$21)/12,1),1),0) -> 0 | K35: ='Pensiones'!T24 -> 0 | L35: ='Pensiones'!U24 -> 0 | M35: =SUM(F35:L35) -> 103323 | N35: =SUMPRODUCT(('Ingresos'!$H$22:$H$26=B35)*'Ingresos'!$G$22:$G$26*(1+('Ingresos'!$E$22:$E$26="CRC")*N($F$8)+('Ingresos'!$E$22:$E$26<>"CRC")*$F$9)^(D35-1)) -> 0 | O35: ='Pensiones'!S24 -> 0 | P35: =SUM(N35:O35) -> 0 | Q35: =M35+P35 -> 103323 | R35: =$W$7*12*(N($F$22)*(1+$F$9)^(D35-1)+(1-N($F$22))*(1+N($F$8))^(D35-1))*IF(D35>$F$19,$F$18,1) -> 79914 | S35: =SUMPRODUCT(('Gastos'!$H$14:$H$17<=B35)*('Gastos'!$H$14:$H$17+'Gastos'!$I$14:$I$17>B35)*'Gastos'!$G$14:$G$17*(1+('Gastos'!$E$14:$E$17="CRC")*N($F$8)+('Gastos'!$E$14:$E$17<>"CRC")*$F$9)^(D35-1)) -> 14530 | T35: =$W$10*(1+IF($V$10="CRC",N($F$8),$F$9))^(D35-1) -> 3632 | U35: =(IF(D35<=$X$11,$W$11*12,0)+IF('Gastos'!$G$28="Sí",0,SUMPRODUCT(('Gastos'!$H$22:$H$26>=B35)*'Gastos'!$G$22:$G$26)*12)+SUMPRODUCT(('Gastos'!$H$43:$H$45<=B35)*('Gastos'!$H$43:$H$45+'Gastos'!$I$43:$I$45-1>=B35)*'Gastos'!$K$43:$K$45)) -> 14400 | V35: =SUM(R35:U35) -> 112476 | W35: =SUMPRODUCT(('Gastos'!$I$33:$I$37=1)*('Gastos'!$H$33:$H$37=B35)*'Gastos'!$G$33:$G$37*(1+('Gastos'!$E$33:$E$37="CRC")*N($F$8)+('Gastos'!$E$33:$E$37<>"CRC")*$F$9)^(D35-1))+SUMPRODUCT(('Gastos'!$I$33:$I$37=2)*('Gastos'!$H$33:$H$37<=B35)*'Gastos'!$G$33:$G$37*(1+('Gastos'!$E$33:$E$37="CRC")*N($F$8)+('Gastos'!$E$33:$E$37<>"CRC")*$F$9)^(D35-1))+SUMPRODUCT(('Retiros del portafolio'!$H$15:$H$18=B35)*'Retiros del portafolio'!$G$15:$G$18*(1+('Retiros del portafolio'!$E$15:$E$18="CRC")*N($F$8)+('Retiros del portafolio'!$E$15:$E$18<>"CRC")*$F$9)^(D35-1)) -> 67806 | X35: =SUMPRODUCT(('Retiros del portafolio'!$H$6:$H$9=B35)*'Retiros del portafolio'!$G$6:$G$9*(1+('Retiros del portafolio'!$E$6:$E$9="CRC")*N($F$8)+('Retiros del portafolio'!$E$6:$E$9<>"CRC")*$F$9)^(D35-1)) -> 48433 | Y35: =W35+X35 -> 116238 | Z35: =V35+Y35 -> 228714 | AA35: =Q35-Z35 -> -125391 | AB35: =SUMPRODUCT(('Desinversiones'!$H$6:$H$10=B35)*('Desinversiones'!$I$6:$I$10=1)*'Desinversiones'!$G$6:$G$10*(1+('Desinversiones'!$E$6:$E$10="CRC")*N($F$8)+('Desinversiones'!$E$6:$E$10<>"CRC")*$F$9)^(D35-1)) -> 217947 | AC35: =SUMPRODUCT(('Desinversiones'!$H$6:$H$10=B35)*('Desinversiones'!$I$6:$I$10=2)*'Desinversiones'!$G$6:$G$10*(1+('Desinversiones'!$E$6:$E$10="CRC")*N($F$8)+('Desinversiones'!$E$6:$E$10<>"CRC")*$F$9)^(D35-1)) -> 0 | AD35: =SUMPRODUCT(('Desinversiones'!$H$6:$H$10=B35)*('Desinversiones'!$I$6:$I$10=3)*'Desinversiones'!$G$6:$G$10*(1+('Desinversiones'!$E$6:$E$10="CRC")*N($F$8)+('Desinversiones'!$E$6:$E$10<>"CRC")*$F$9)^(D35-1)) -> 0 | AE35: =SUM(AB35:AD35) -> 217947 | AF35: =AE35 -> 217947 | AG35: =AJ34 -> 296131 | AH35: =AG35*$F$13 -> 17345 | AI35: =AA35+AF35 -> 92555 | AJ35: =AG35+AH35+AI35+AM35 -> 406031 | AK35: =AJ35/(1+$F$9)^(D35-1+$F$24/12) -> 332145 | AL35: =IF(AG35<=0,0,MAX(0,-AI35)/AG35) -> 0 | AM35: =MAX(0,-(AG35+AH35+AI35)) -> 0
B36: =B35+1 -> 2032 | C36: =C35+1 -> 52 | D36: =D35+1 -> 7 | E36: =IF(D36<=$F$19,"Acumulación","Retiro") -> Acumulación | F36: =IF(D36<=$P$7,$N$7*12*(1+IF($M$7="CRC",N($F$8),$F$9))^(D36-1),0) -> 90579 | G36: =IF(D36<=$P$8,$N$8*12*(1+IF($M$8="CRC",N($F$8),$F$9))^(D36-1),0) -> 0 | H36: =IF(AND($N$9>0,D36>=$O$9,D36<=$P$9),$N$9*12*(1+IF($M$9="CRC",N($F$8),$F$9))^(D36-1),0) -> 16774 | I36: =SUMPRODUCT(('Ingresos'!$H$14:$H$17>=B36)*'Ingresos'!$G$14:$G$17*(1+('Ingresos'!$E$14:$E$17="CRC")*N($F$8)+('Ingresos'!$E$14:$E$17<>"CRC")*$F$9)^(D36-1))*12 -> 0 | J36: =IF(AND($N$10>0,D36>=N($O$10)),$N$10*12*(1+IF($M$10="CRC",N($F$8),$F$9))^(N($O$10)-1)*(1+N($F$10))^(D36-N($O$10))*IF(D36=N($O$10),IF(AND(ISNUMBER($F$21),N($F$20)>=$C$30),(12-$F$21)/12,1),1),0) -> 0 | K36: ='Pensiones'!T25 -> 0 | L36: ='Pensiones'!U25 -> 0 | M36: =SUM(F36:L36) -> 107352 | N36: =SUMPRODUCT(('Ingresos'!$H$22:$H$26=B36)*'Ingresos'!$G$22:$G$26*(1+('Ingresos'!$E$22:$E$26="CRC")*N($F$8)+('Ingresos'!$E$22:$E$26<>"CRC")*$F$9)^(D36-1)) -> 150964 | O36: ='Pensiones'!S25 -> 0 | P36: =SUM(N36:O36) -> 150964 | Q36: =M36+P36 -> 258317 | R36: =$W$7*12*(N($F$22)*(1+$F$9)^(D36-1)+(1-N($F$22))*(1+N($F$8))^(D36-1))*IF(D36>$F$19,$F$18,1) -> 83030 | S36: =SUMPRODUCT(('Gastos'!$H$14:$H$17<=B36)*('Gastos'!$H$14:$H$17+'Gastos'!$I$14:$I$17>B36)*'Gastos'!$G$14:$G$17*(1+('Gastos'!$E$14:$E$17="CRC")*N($F$8)+('Gastos'!$E$14:$E$17<>"CRC")*$F$9)^(D36-1)) -> 15096 | T36: =$W$10*(1+IF($V$10="CRC",N($F$8),$F$9))^(D36-1) -> 3774 | U36: =(IF(D36<=$X$11,$W$11*12,0)+IF('Gastos'!$G$28="Sí",0,SUMPRODUCT(('Gastos'!$H$22:$H$26>=B36)*'Gastos'!$G$22:$G$26)*12)+SUMPRODUCT(('Gastos'!$H$43:$H$45<=B36)*('Gastos'!$H$43:$H$45+'Gastos'!$I$43:$I$45-1>=B36)*'Gastos'!$K$43:$K$45)) -> 14400 | V36: =SUM(R36:U36) -> 116301 | W36: =SUMPRODUCT(('Gastos'!$I$33:$I$37=1)*('Gastos'!$H$33:$H$37=B36)*'Gastos'!$G$33:$G$37*(1+('Gastos'!$E$33:$E$37="CRC")*N($F$8)+('Gastos'!$E$33:$E$37<>"CRC")*$F$9)^(D36-1))+SUMPRODUCT(('Gastos'!$I$33:$I$37=2)*('Gastos'!$H$33:$H$37<=B36)*'Gastos'!$G$33:$G$37*(1+('Gastos'!$E$33:$E$37="CRC")*N($F$8)+('Gastos'!$E$33:$E$37<>"CRC")*$F$9)^(D36-1))+SUMPRODUCT(('Retiros del portafolio'!$H$15:$H$18=B36)*'Retiros del portafolio'!$G$15:$G$18*(1+('Retiros del portafolio'!$E$15:$E$18="CRC")*N($F$8)+('Retiros del portafolio'!$E$15:$E$18<>"CRC")*$F$9)^(D36-1)) -> 7548 | X36: =SUMPRODUCT(('Retiros del portafolio'!$H$6:$H$9=B36)*'Retiros del portafolio'!$G$6:$G$9*(1+('Retiros del portafolio'!$E$6:$E$9="CRC")*N($F$8)+('Retiros del portafolio'!$E$6:$E$9<>"CRC")*$F$9)^(D36-1)) -> 0 | Y36: =W36+X36 -> 7548 | Z36: =V36+Y36 -> 123849 | AA36: =Q36-Z36 -> 134468 | AB36: =SUMPRODUCT(('Desinversiones'!$H$6:$H$10=B36)*('Desinversiones'!$I$6:$I$10=1)*'Desinversiones'!$G$6:$G$10*(1+('Desinversiones'!$E$6:$E$10="CRC")*N($F$8)+('Desinversiones'!$E$6:$E$10<>"CRC")*$F$9)^(D36-1)) -> 0 | AC36: =SUMPRODUCT(('Desinversiones'!$H$6:$H$10=B36)*('Desinversiones'!$I$6:$I$10=2)*'Desinversiones'!$G$6:$G$10*(1+('Desinversiones'!$E$6:$E$10="CRC")*N($F$8)+('Desinversiones'!$E$6:$E$10<>"CRC")*$F$9)^(D36-1)) -> 0 | AD36: =SUMPRODUCT(('Desinversiones'!$H$6:$H$10=B36)*('Desinversiones'!$I$6:$I$10=3)*'Desinversiones'!$G$6:$G$10*(1+('Desinversiones'!$E$6:$E$10="CRC")*N($F$8)+('Desinversiones'!$E$6:$E$10<>"CRC")*$F$9)^(D36-1)) -> 0 | AE36: =SUM(AB36:AD36) -> 0 | AF36: =AE36 -> 0 | AG36: =AJ35 -> 406031 | AH36: =AG36*$F$13 -> 23782 | AI36: =AA36+AF36 -> 134468 | AJ36: =AG36+AH36+AI36+AM36 -> 564281 | AK36: =AJ36/(1+$F$9)^(D36-1+$F$24/12) -> 444271 | AL36: =IF(AG36<=0,0,MAX(0,-AI36)/AG36) -> 0 | AM36: =MAX(0,-(AG36+AH36+AI36)) -> 0
B37: =B36+1 -> 2033 | C37: =C36+1 -> 53 | D37: =D36+1 -> 8 | E37: =IF(D37<=$F$19,"Acumulación","Retiro") -> Acumulación | F37: =IF(D37<=$P$7,$N$7*12*(1+IF($M$7="CRC",N($F$8),$F$9))^(D37-1),0) -> 94111 | G37: =IF(D37<=$P$8,$N$8*12*(1+IF($M$8="CRC",N($F$8),$F$9))^(D37-1),0) -> 0 | H37: =IF(AND($N$9>0,D37>=$O$9,D37<=$P$9),$N$9*12*(1+IF($M$9="CRC",N($F$8),$F$9))^(D37-1),0) -> 17428 | I37: =SUMPRODUCT(('Ingresos'!$H$14:$H$17>=B37)*'Ingresos'!$G$14:$G$17*(1+('Ingresos'!$E$14:$E$17="CRC")*N($F$8)+('Ingresos'!$E$14:$E$17<>"CRC")*$F$9)^(D37-1))*12 -> 0 | J37: =IF(AND($N$10>0,D37>=N($O$10)),$N$10*12*(1+IF($M$10="CRC",N($F$8),$F$9))^(N($O$10)-1)*(1+N($F$10))^(D37-N($O$10))*IF(D37=N($O$10),IF(AND(ISNUMBER($F$21),N($F$20)>=$C$30),(12-$F$21)/12,1),1),0) -> 0 | K37: ='Pensiones'!T26 -> 0 | L37: ='Pensiones'!U26 -> 0 | M37: =SUM(F37:L37) -> 111539 | N37: =SUMPRODUCT(('Ingresos'!$H$22:$H$26=B37)*'Ingresos'!$G$22:$G$26*(1+('Ingresos'!$E$22:$E$26="CRC")*N($F$8)+('Ingresos'!$E$22:$E$26<>"CRC")*$F$9)^(D37-1)) -> 0 | O37: ='Pensiones'!S26 -> 0 | P37: =SUM(N37:O37) -> 0 | Q37: =M37+P37 -> 111539 | R37: =$W$7*12*(N($F$22)*(1+$F$9)^(D37-1)+(1-N($F$22))*(1+N($F$8))^(D37-1))*IF(D37>$F$19,$F$18,1) -> 86269 | S37: =SUMPRODUCT(('Gastos'!$H$14:$H$17<=B37)*('Gastos'!$H$14:$H$17+'Gastos'!$I$14:$I$17>B37)*'Gastos'!$G$14:$G$17*(1+('Gastos'!$E$14:$E$17="CRC")*N($F$8)+('Gastos'!$E$14:$E$17<>"CRC")*$F$9)^(D37-1)) -> 15685 | T37: =$W$10*(1+IF($V$10="CRC",N($F$8),$F$9))^(D37-1) -> 3921 | U37: =(IF(D37<=$X$11,$W$11*12,0)+IF('Gastos'!$G$28="Sí",0,SUMPRODUCT(('Gastos'!$H$22:$H$26>=B37)*'Gastos'!$G$22:$G$26)*12)+SUMPRODUCT(('Gastos'!$H$43:$H$45<=B37)*('Gastos'!$H$43:$H$45+'Gastos'!$I$43:$I$45-1>=B37)*'Gastos'!$K$43:$K$45)) -> 14400 | V37: =SUM(R37:U37) -> 120275 | W37: =SUMPRODUCT(('Gastos'!$I$33:$I$37=1)*('Gastos'!$H$33:$H$37=B37)*'Gastos'!$G$33:$G$37*(1+('Gastos'!$E$33:$E$37="CRC")*N($F$8)+('Gastos'!$E$33:$E$37<>"CRC")*$F$9)^(D37-1))+SUMPRODUCT(('Gastos'!$I$33:$I$37=2)*('Gastos'!$H$33:$H$37<=B37)*'Gastos'!$G$33:$G$37*(1+('Gastos'!$E$33:$E$37="CRC")*N($F$8)+('Gastos'!$E$33:$E$37<>"CRC")*$F$9)^(D37-1))+SUMPRODUCT(('Retiros del portafolio'!$H$15:$H$18=B37)*'Retiros del portafolio'!$G$15:$G$18*(1+('Retiros del portafolio'!$E$15:$E$18="CRC")*N($F$8)+('Retiros del portafolio'!$E$15:$E$18<>"CRC")*$F$9)^(D37-1)) -> 7843 | X37: =SUMPRODUCT(('Retiros del portafolio'!$H$6:$H$9=B37)*'Retiros del portafolio'!$G$6:$G$9*(1+('Retiros del portafolio'!$E$6:$E$9="CRC")*N($F$8)+('Retiros del portafolio'!$E$6:$E$9<>"CRC")*$F$9)^(D37-1)) -> 0 | Y37: =W37+X37 -> 7843 | Z37: =V37+Y37 -> 128118 | AA37: =Q37-Z37 -> -16579 | AB37: =SUMPRODUCT(('Desinversiones'!$H$6:$H$10=B37)*('Desinversiones'!$I$6:$I$10=1)*'Desinversiones'!$G$6:$G$10*(1+('Desinversiones'!$E$6:$E$10="CRC")*N($F$8)+('Desinversiones'!$E$6:$E$10<>"CRC")*$F$9)^(D37-1)) -> 0 | AC37: =SUMPRODUCT(('Desinversiones'!$H$6:$H$10=B37)*('Desinversiones'!$I$6:$I$10=2)*'Desinversiones'!$G$6:$G$10*(1+('Desinversiones'!$E$6:$E$10="CRC")*N($F$8)+('Desinversiones'!$E$6:$E$10<>"CRC")*$F$9)^(D37-1)) -> 0 | AD37: =SUMPRODUCT(('Desinversiones'!$H$6:$H$10=B37)*('Desinversiones'!$I$6:$I$10=3)*'Desinversiones'!$G$6:$G$10*(1+('Desinversiones'!$E$6:$E$10="CRC")*N($F$8)+('Desinversiones'!$E$6:$E$10<>"CRC")*$F$9)^(D37-1)) -> 196065 | AE37: =SUM(AB37:AD37) -> 196065 | AF37: =AE37 -> 196065 | AG37: =AJ36 -> 564281 | AH37: =AG37*$F$13 -> 33051 | AI37: =AA37+AF37 -> 179487 | AJ37: =AG37+AH37+AI37+AM37 -> 776819 | AK37: =AJ37/(1+$F$9)^(D37-1+$F$24/12) -> 588650 | AL37: =IF(AG37<=0,0,MAX(0,-AI37)/AG37) -> 0 | AM37: =MAX(0,-(AG37+AH37+AI37)) -> 0
B38: =B37+1 -> 2034 | C38: =C37+1 -> 54 | D38: =D37+1 -> 9 | E38: =IF(D38<=$F$19,"Acumulación","Retiro") -> Acumulación | F38: =IF(D38<=$P$7,$N$7*12*(1+IF($M$7="CRC",N($F$8),$F$9))^(D38-1),0) -> 97782 | G38: =IF(D38<=$P$8,$N$8*12*(1+IF($M$8="CRC",N($F$8),$F$9))^(D38-1),0) -> 0 | H38: =IF(AND($N$9>0,D38>=$O$9,D38<=$P$9),$N$9*12*(1+IF($M$9="CRC",N($F$8),$F$9))^(D38-1),0) -> 18108 | I38: =SUMPRODUCT(('Ingresos'!$H$14:$H$17>=B38)*'Ingresos'!$G$14:$G$17*(1+('Ingresos'!$E$14:$E$17="CRC")*N($F$8)+('Ingresos'!$E$14:$E$17<>"CRC")*$F$9)^(D38-1))*12 -> 0 | J38: =IF(AND($N$10>0,D38>=N($O$10)),$N$10*12*(1+IF($M$10="CRC",N($F$8),$F$9))^(N($O$10)-1)*(1+N($F$10))^(D38-N($O$10))*IF(D38=N($O$10),IF(AND(ISNUMBER($F$21),N($F$20)>=$C$30),(12-$F$21)/12,1),1),0) -> 0 | K38: ='Pensiones'!T27 -> 0 | L38: ='Pensiones'!U27 -> 0 | M38: =SUM(F38:L38) -> 115889 | N38: =SUMPRODUCT(('Ingresos'!$H$22:$H$26=B38)*'Ingresos'!$G$22:$G$26*(1+('Ingresos'!$E$22:$E$26="CRC")*N($F$8)+('Ingresos'!$E$22:$E$26<>"CRC")*$F$9)^(D38-1)) -> 0 | O38: ='Pensiones'!S27 -> 0 | P38: =SUM(N38:O38) -> 0 | Q38: =M38+P38 -> 115889 | R38: =$W$7*12*(N($F$22)*(1+$F$9)^(D38-1)+(1-N($F$22))*(1+N($F$8))^(D38-1))*IF(D38>$F$19,$F$18,1) -> 89633 | S38: =SUMPRODUCT(('Gastos'!$H$14:$H$17<=B38)*('Gastos'!$H$14:$H$17+'Gastos'!$I$14:$I$17>B38)*'Gastos'!$G$14:$G$17*(1+('Gastos'!$E$14:$E$17="CRC")*N($F$8)+('Gastos'!$E$14:$E$17<>"CRC")*$F$9)^(D38-1)) -> 16297 | T38: =$W$10*(1+IF($V$10="CRC",N($F$8),$F$9))^(D38-1) -> 4074 | U38: =(IF(D38<=$X$11,$W$11*12,0)+IF('Gastos'!$G$28="Sí",0,SUMPRODUCT(('Gastos'!$H$22:$H$26>=B38)*'Gastos'!$G$22:$G$26)*12)+SUMPRODUCT(('Gastos'!$H$43:$H$45<=B38)*('Gastos'!$H$43:$H$45+'Gastos'!$I$43:$I$45-1>=B38)*'Gastos'!$K$43:$K$45)) -> 14400 | V38: =SUM(R38:U38) -> 124404 | W38: =SUMPRODUCT(('Gastos'!$I$33:$I$37=1)*('Gastos'!$H$33:$H$37=B38)*'Gastos'!$G$33:$G$37*(1+('Gastos'!$E$33:$E$37="CRC")*N($F$8)+('Gastos'!$E$33:$E$37<>"CRC")*$F$9)^(D38-1))+SUMPRODUCT(('Gastos'!$I$33:$I$37=2)*('Gastos'!$H$33:$H$37<=B38)*'Gastos'!$G$33:$G$37*(1+('Gastos'!$E$33:$E$37="CRC")*N($F$8)+('Gastos'!$E$33:$E$37<>"CRC")*$F$9)^(D38-1))+SUMPRODUCT(('Retiros del portafolio'!$H$15:$H$18=B38)*'Retiros del portafolio'!$G$15:$G$18*(1+('Retiros del portafolio'!$E$15:$E$18="CRC")*N($F$8)+('Retiros del portafolio'!$E$15:$E$18<>"CRC")*$F$9)^(D38-1)) -> 8148 | X38: =SUMPRODUCT(('Retiros del portafolio'!$H$6:$H$9=B38)*'Retiros del portafolio'!$G$6:$G$9*(1+('Retiros del portafolio'!$E$6:$E$9="CRC")*N($F$8)+('Retiros del portafolio'!$E$6:$E$9<>"CRC")*$F$9)^(D38-1)) -> 0 | Y38: =W38+X38 -> 8148 | Z38: =V38+Y38 -> 132553 | AA38: =Q38-Z38 -> -16663 | AB38: =SUMPRODUCT(('Desinversiones'!$H$6:$H$10=B38)*('Desinversiones'!$I$6:$I$10=1)*'Desinversiones'!$G$6:$G$10*(1+('Desinversiones'!$E$6:$E$10="CRC")*N($F$8)+('Desinversiones'!$E$6:$E$10<>"CRC")*$F$9)^(D38-1)) -> 0 | AC38: =SUMPRODUCT(('Desinversiones'!$H$6:$H$10=B38)*('Desinversiones'!$I$6:$I$10=2)*'Desinversiones'!$G$6:$G$10*(1+('Desinversiones'!$E$6:$E$10="CRC")*N($F$8)+('Desinversiones'!$E$6:$E$10<>"CRC")*$F$9)^(D38-1)) -> 0 | AD38: =SUMPRODUCT(('Desinversiones'!$H$6:$H$10=B38)*('Desinversiones'!$I$6:$I$10=3)*'Desinversiones'!$G$6:$G$10*(1+('Desinversiones'!$E$6:$E$10="CRC")*N($F$8)+('Desinversiones'!$E$6:$E$10<>"CRC")*$F$9)^(D38-1)) -> 0 | AE38: =SUM(AB38:AD38) -> 0 | AF38: =AE38 -> 0 | AG38: =AJ37 -> 776819 | AH38: =AG38*$F$13 -> 45500 | AI38: =AA38+AF38 -> -16663 | AJ38: =AG38+AH38+AI38+AM38 -> 805656 | AK38: =AJ38/(1+$F$9)^(D38-1+$F$24/12) -> 587586 | AL38: =IF(AG38<=0,0,MAX(0,-AI38)/AG38) -> 0.021450893 | AM38: =MAX(0,-(AG38+AH38+AI38)) -> 0
B39: =B38+1 -> 2035 | C39: =C38+1 -> 55 | D39: =D38+1 -> 10 | E39: =IF(D39<=$F$19,"Acumulación","Retiro") -> Acumulación | F39: =IF(D39<=$P$7,$N$7*12*(1+IF($M$7="CRC",N($F$8),$F$9))^(D39-1),0) -> 101595 | G39: =IF(D39<=$P$8,$N$8*12*(1+IF($M$8="CRC",N($F$8),$F$9))^(D39-1),0) -> 0 | H39: =IF(AND($N$9>0,D39>=$O$9,D39<=$P$9),$N$9*12*(1+IF($M$9="CRC",N($F$8),$F$9))^(D39-1),0) -> 18814 | I39: =SUMPRODUCT(('Ingresos'!$H$14:$H$17>=B39)*'Ingresos'!$G$14:$G$17*(1+('Ingresos'!$E$14:$E$17="CRC")*N($F$8)+('Ingresos'!$E$14:$E$17<>"CRC")*$F$9)^(D39-1))*12 -> 0 | J39: =IF(AND($N$10>0,D39>=N($O$10)),$N$10*12*(1+IF($M$10="CRC",N($F$8),$F$9))^(N($O$10)-1)*(1+N($F$10))^(D39-N($O$10))*IF(D39=N($O$10),IF(AND(ISNUMBER($F$21),N($F$20)>=$C$30),(12-$F$21)/12,1),1),0) -> 0 | K39: ='Pensiones'!T28 -> 0 | L39: ='Pensiones'!U28 -> 0 | M39: =SUM(F39:L39) -> 120409 | N39: =SUMPRODUCT(('Ingresos'!$H$22:$H$26=B39)*'Ingresos'!$G$22:$G$26*(1+('Ingresos'!$E$22:$E$26="CRC")*N($F$8)+('Ingresos'!$E$22:$E$26<>"CRC")*$F$9)^(D39-1)) -> 0 | O39: ='Pensiones'!S28 -> 0 | P39: =SUM(N39:O39) -> 0 | Q39: =M39+P39 -> 120409 | R39: =$W$7*12*(N($F$22)*(1+$F$9)^(D39-1)+(1-N($F$22))*(1+N($F$8))^(D39-1))*IF(D39>$F$19,$F$18,1) -> 93129 | S39: =SUMPRODUCT(('Gastos'!$H$14:$H$17<=B39)*('Gastos'!$H$14:$H$17+'Gastos'!$I$14:$I$17>B39)*'Gastos'!$G$14:$G$17*(1+('Gastos'!$E$14:$E$17="CRC")*N($F$8)+('Gastos'!$E$14:$E$17<>"CRC")*$F$9)^(D39-1)) -> 0 | T39: =$W$10*(1+IF($V$10="CRC",N($F$8),$F$9))^(D39-1) -> 4233 | U39: =(IF(D39<=$X$11,$W$11*12,0)+IF('Gastos'!$G$28="Sí",0,SUMPRODUCT(('Gastos'!$H$22:$H$26>=B39)*'Gastos'!$G$22:$G$26)*12)+SUMPRODUCT(('Gastos'!$H$43:$H$45<=B39)*('Gastos'!$H$43:$H$45+'Gastos'!$I$43:$I$45-1>=B39)*'Gastos'!$K$43:$K$45)) -> 14400 | V39: =SUM(R39:U39) -> 111762 | W39: =SUMPRODUCT(('Gastos'!$I$33:$I$37=1)*('Gastos'!$H$33:$H$37=B39)*'Gastos'!$G$33:$G$37*(1+('Gastos'!$E$33:$E$37="CRC")*N($F$8)+('Gastos'!$E$33:$E$37<>"CRC")*$F$9)^(D39-1))+SUMPRODUCT(('Gastos'!$I$33:$I$37=2)*('Gastos'!$H$33:$H$37<=B39)*'Gastos'!$G$33:$G$37*(1+('Gastos'!$E$33:$E$37="CRC")*N($F$8)+('Gastos'!$E$33:$E$37<>"CRC")*$F$9)^(D39-1))+SUMPRODUCT(('Retiros del portafolio'!$H$15:$H$18=B39)*'Retiros del portafolio'!$G$15:$G$18*(1+('Retiros del portafolio'!$E$15:$E$18="CRC")*N($F$8)+('Retiros del portafolio'!$E$15:$E$18<>"CRC")*$F$9)^(D39-1)) -> 8466 | X39: =SUMPRODUCT(('Retiros del portafolio'!$H$6:$H$9=B39)*'Retiros del portafolio'!$G$6:$G$9*(1+('Retiros del portafolio'!$E$6:$E$9="CRC")*N($F$8)+('Retiros del portafolio'!$E$6:$E$9<>"CRC")*$F$9)^(D39-1)) -> 0 | Y39: =W39+X39 -> 8466 | Z39: =V39+Y39 -> 120228 | AA39: =Q39-Z39 -> 181 | AB39: =SUMPRODUCT(('Desinversiones'!$H$6:$H$10=B39)*('Desinversiones'!$I$6:$I$10=1)*'Desinversiones'!$G$6:$G$10*(1+('Desinversiones'!$E$6:$E$10="CRC")*N($F$8)+('Desinversiones'!$E$6:$E$10<>"CRC")*$F$9)^(D39-1)) -> 0 | AC39: =SUMPRODUCT(('Desinversiones'!$H$6:$H$10=B39)*('Desinversiones'!$I$6:$I$10=2)*'Desinversiones'!$G$6:$G$10*(1+('Desinversiones'!$E$6:$E$10="CRC")*N($F$8)+('Desinversiones'!$E$6:$E$10<>"CRC")*$F$9)^(D39-1)) -> 0 | AD39: =SUMPRODUCT(('Desinversiones'!$H$6:$H$10=B39)*('Desinversiones'!$I$6:$I$10=3)*'Desinversiones'!$G$6:$G$10*(1+('Desinversiones'!$E$6:$E$10="CRC")*N($F$8)+('Desinversiones'!$E$6:$E$10<>"CRC")*$F$9)^(D39-1)) -> 0 | AE39: =SUM(AB39:AD39) -> 0 | AF39: =AE39 -> 0 | AG39: =AJ38 -> 805656 | AH39: =AG39*$F$13 -> 47189 | AI39: =AA39+AF39 -> 181 | AJ39: =AG39+AH39+AI39+AM39 -> 853026 | AK39: =AJ39/(1+$F$9)^(D39-1+$F$24/12) -> 598781 | AL39: =IF(AG39<=0,0,MAX(0,-AI39)/AG39) -> 0 | AM39: =MAX(0,-(AG39+AH39+AI39)) -> 0
B40: =B39+1 -> 2036 | C40: =C39+1 -> 56 | D40: =D39+1 -> 11 | E40: =IF(D40<=$F$19,"Acumulación","Retiro") -> Acumulación | F40: =IF(D40<=$P$7,$N$7*12*(1+IF($M$7="CRC",N($F$8),$F$9))^(D40-1),0) -> 105557 | G40: =IF(D40<=$P$8,$N$8*12*(1+IF($M$8="CRC",N($F$8),$F$9))^(D40-1),0) -> 0 | H40: =IF(AND($N$9>0,D40>=$O$9,D40<=$P$9),$N$9*12*(1+IF($M$9="CRC",N($F$8),$F$9))^(D40-1),0) -> 19548 | I40: =SUMPRODUCT(('Ingresos'!$H$14:$H$17>=B40)*'Ingresos'!$G$14:$G$17*(1+('Ingresos'!$E$14:$E$17="CRC")*N($F$8)+('Ingresos'!$E$14:$E$17<>"CRC")*$F$9)^(D40-1))*12 -> 0 | J40: =IF(AND($N$10>0,D40>=N($O$10)),$N$10*12*(1+IF($M$10="CRC",N($F$8),$F$9))^(N($O$10)-1)*(1+N($F$10))^(D40-N($O$10))*IF(D40=N($O$10),IF(AND(ISNUMBER($F$21),N($F$20)>=$C$30),(12-$F$21)/12,1),1),0) -> 0 | K40: ='Pensiones'!T29 -> 0 | L40: ='Pensiones'!U29 -> 0 | M40: =SUM(F40:L40) -> 125105 | N40: =SUMPRODUCT(('Ingresos'!$H$22:$H$26=B40)*'Ingresos'!$G$22:$G$26*(1+('Ingresos'!$E$22:$E$26="CRC")*N($F$8)+('Ingresos'!$E$22:$E$26<>"CRC")*$F$9)^(D40-1)) -> 0 | O40: ='Pensiones'!S29 -> 0 | P40: =SUM(N40:O40) -> 0 | Q40: =M40+P40 -> 125105 | R40: =$W$7*12*(N($F$22)*(1+$F$9)^(D40-1)+(1-N($F$22))*(1+N($F$8))^(D40-1))*IF(D40>$F$19,$F$18,1) -> 96761 | S40: =SUMPRODUCT(('Gastos'!$H$14:$H$17<=B40)*('Gastos'!$H$14:$H$17+'Gastos'!$I$14:$I$17>B40)*'Gastos'!$G$14:$G$17*(1+('Gastos'!$E$14:$E$17="CRC")*N($F$8)+('Gastos'!$E$14:$E$17<>"CRC")*$F$9)^(D40-1)) -> 0 | T40: =$W$10*(1+IF($V$10="CRC",N($F$8),$F$9))^(D40-1) -> 4398 | U40: =(IF(D40<=$X$11,$W$11*12,0)+IF('Gastos'!$G$28="Sí",0,SUMPRODUCT(('Gastos'!$H$22:$H$26>=B40)*'Gastos'!$G$22:$G$26)*12)+SUMPRODUCT(('Gastos'!$H$43:$H$45<=B40)*('Gastos'!$H$43:$H$45+'Gastos'!$I$43:$I$45-1>=B40)*'Gastos'!$K$43:$K$45)) -> 14400 | V40: =SUM(R40:U40) -> 115559 | W40: =SUMPRODUCT(('Gastos'!$I$33:$I$37=1)*('Gastos'!$H$33:$H$37=B40)*'Gastos'!$G$33:$G$37*(1+('Gastos'!$E$33:$E$37="CRC")*N($F$8)+('Gastos'!$E$33:$E$37<>"CRC")*$F$9)^(D40-1))+SUMPRODUCT(('Gastos'!$I$33:$I$37=2)*('Gastos'!$H$33:$H$37<=B40)*'Gastos'!$G$33:$G$37*(1+('Gastos'!$E$33:$E$37="CRC")*N($F$8)+('Gastos'!$E$33:$E$37<>"CRC")*$F$9)^(D40-1))+SUMPRODUCT(('Retiros del portafolio'!$H$15:$H$18=B40)*'Retiros del portafolio'!$G$15:$G$18*(1+('Retiros del portafolio'!$E$15:$E$18="CRC")*N($F$8)+('Retiros del portafolio'!$E$15:$E$18<>"CRC")*$F$9)^(D40-1)) -> 8796 | X40: =SUMPRODUCT(('Retiros del portafolio'!$H$6:$H$9=B40)*'Retiros del portafolio'!$G$6:$G$9*(1+('Retiros del portafolio'!$E$6:$E$9="CRC")*N($F$8)+('Retiros del portafolio'!$E$6:$E$9<>"CRC")*$F$9)^(D40-1)) -> 0 | Y40: =W40+X40 -> 8796 | Z40: =V40+Y40 -> 124355 | AA40: =Q40-Z40 -> 749 | AB40: =SUMPRODUCT(('Desinversiones'!$H$6:$H$10=B40)*('Desinversiones'!$I$6:$I$10=1)*'Desinversiones'!$G$6:$G$10*(1+('Desinversiones'!$E$6:$E$10="CRC")*N($F$8)+('Desinversiones'!$E$6:$E$10<>"CRC")*$F$9)^(D40-1)) -> 0 | AC40: =SUMPRODUCT(('Desinversiones'!$H$6:$H$10=B40)*('Desinversiones'!$I$6:$I$10=2)*'Desinversiones'!$G$6:$G$10*(1+('Desinversiones'!$E$6:$E$10="CRC")*N($F$8)+('Desinversiones'!$E$6:$E$10<>"CRC")*$F$9)^(D40-1)) -> 0 | AD40: =SUMPRODUCT(('Desinversiones'!$H$6:$H$10=B40)*('Desinversiones'!$I$6:$I$10=3)*'Desinversiones'!$G$6:$G$10*(1+('Desinversiones'!$E$6:$E$10="CRC")*N($F$8)+('Desinversiones'!$E$6:$E$10<>"CRC")*$F$9)^(D40-1)) -> 0 | AE40: =SUM(AB40:AD40) -> 0 | AF40: =AE40 -> 0 | AG40: =AJ39 -> 853026 | AH40: =AG40*$F$13 -> 49964 | AI40: =AA40+AF40 -> 749 | AJ40: =AG40+AH40+AI40+AM40 -> 903739 | AK40: =AJ40/(1+$F$9)^(D40-1+$F$24/12) -> 610568 | AL40: =IF(AG40<=0,0,MAX(0,-AI40)/AG40) -> 0 | AM40: =MAX(0,-(AG40+AH40+AI40)) -> 0
B41: =B40+1 -> 2037 | C41: =C40+1 -> 57 | D41: =D40+1 -> 12 | E41: =IF(D41<=$F$19,"Acumulación","Retiro") -> Acumulación | F41: =IF(D41<=$P$7,$N$7*12*(1+IF($M$7="CRC",N($F$8),$F$9))^(D41-1),0) -> 109674 | G41: =IF(D41<=$P$8,$N$8*12*(1+IF($M$8="CRC",N($F$8),$F$9))^(D41-1),0) -> 0 | H41: =IF(AND($N$9>0,D41>=$O$9,D41<=$P$9),$N$9*12*(1+IF($M$9="CRC",N($F$8),$F$9))^(D41-1),0) -> 20310 | I41: =SUMPRODUCT(('Ingresos'!$H$14:$H$17>=B41)*'Ingresos'!$G$14:$G$17*(1+('Ingresos'!$E$14:$E$17="CRC")*N($F$8)+('Ingresos'!$E$14:$E$17<>"CRC")*$F$9)^(D41-1))*12 -> 0 | J41: =IF(AND($N$10>0,D41>=N($O$10)),$N$10*12*(1+IF($M$10="CRC",N($F$8),$F$9))^(N($O$10)-1)*(1+N($F$10))^(D41-N($O$10))*IF(D41=N($O$10),IF(AND(ISNUMBER($F$21),N($F$20)>=$C$30),(12-$F$21)/12,1),1),0) -> 0 | K41: ='Pensiones'!T30 -> 0 | L41: ='Pensiones'!U30 -> 0 | M41: =SUM(F41:L41) -> 129984 | N41: =SUMPRODUCT(('Ingresos'!$H$22:$H$26=B41)*'Ingresos'!$G$22:$G$26*(1+('Ingresos'!$E$22:$E$26="CRC")*N($F$8)+('Ingresos'!$E$22:$E$26<>"CRC")*$F$9)^(D41-1)) -> 0 | O41: ='Pensiones'!S30 -> 0 | P41: =SUM(N41:O41) -> 0 | Q41: =M41+P41 -> 129984 | R41: =$W$7*12*(N($F$22)*(1+$F$9)^(D41-1)+(1-N($F$22))*(1+N($F$8))^(D41-1))*IF(D41>$F$19,$F$18,1) -> 100534 | S41: =SUMPRODUCT(('Gastos'!$H$14:$H$17<=B41)*('Gastos'!$H$14:$H$17+'Gastos'!$I$14:$I$17>B41)*'Gastos'!$G$14:$G$17*(1+('Gastos'!$E$14:$E$17="CRC")*N($F$8)+('Gastos'!$E$14:$E$17<>"CRC")*$F$9)^(D41-1)) -> 0 | T41: =$W$10*(1+IF($V$10="CRC",N($F$8),$F$9))^(D41-1) -> 4570 | U41: =(IF(D41<=$X$11,$W$11*12,0)+IF('Gastos'!$G$28="Sí",0,SUMPRODUCT(('Gastos'!$H$22:$H$26>=B41)*'Gastos'!$G$22:$G$26)*12)+SUMPRODUCT(('Gastos'!$H$43:$H$45<=B41)*('Gastos'!$H$43:$H$45+'Gastos'!$I$43:$I$45-1>=B41)*'Gastos'!$K$43:$K$45)) -> 14400 | V41: =SUM(R41:U41) -> 119504 | W41: =SUMPRODUCT(('Gastos'!$I$33:$I$37=1)*('Gastos'!$H$33:$H$37=B41)*'Gastos'!$G$33:$G$37*(1+('Gastos'!$E$33:$E$37="CRC")*N($F$8)+('Gastos'!$E$33:$E$37<>"CRC")*$F$9)^(D41-1))+SUMPRODUCT(('Gastos'!$I$33:$I$37=2)*('Gastos'!$H$33:$H$37<=B41)*'Gastos'!$G$33:$G$37*(1+('Gastos'!$E$33:$E$37="CRC")*N($F$8)+('Gastos'!$E$33:$E$37<>"CRC")*$F$9)^(D41-1))+SUMPRODUCT(('Retiros del portafolio'!$H$15:$H$18=B41)*'Retiros del portafolio'!$G$15:$G$18*(1+('Retiros del portafolio'!$E$15:$E$18="CRC")*N($F$8)+('Retiros del portafolio'!$E$15:$E$18<>"CRC")*$F$9)^(D41-1)) -> 9139 | X41: =SUMPRODUCT(('Retiros del portafolio'!$H$6:$H$9=B41)*'Retiros del portafolio'!$G$6:$G$9*(1+('Retiros del portafolio'!$E$6:$E$9="CRC")*N($F$8)+('Retiros del portafolio'!$E$6:$E$9<>"CRC")*$F$9)^(D41-1)) -> 0 | Y41: =W41+X41 -> 9139 | Z41: =V41+Y41 -> 128644 | AA41: =Q41-Z41 -> 1340 | AB41: =SUMPRODUCT(('Desinversiones'!$H$6:$H$10=B41)*('Desinversiones'!$I$6:$I$10=1)*'Desinversiones'!$G$6:$G$10*(1+('Desinversiones'!$E$6:$E$10="CRC")*N($F$8)+('Desinversiones'!$E$6:$E$10<>"CRC")*$F$9)^(D41-1)) -> 0 | AC41: =SUMPRODUCT(('Desinversiones'!$H$6:$H$10=B41)*('Desinversiones'!$I$6:$I$10=2)*'Desinversiones'!$G$6:$G$10*(1+('Desinversiones'!$E$6:$E$10="CRC")*N($F$8)+('Desinversiones'!$E$6:$E$10<>"CRC")*$F$9)^(D41-1)) -> 0 | AD41: =SUMPRODUCT(('Desinversiones'!$H$6:$H$10=B41)*('Desinversiones'!$I$6:$I$10=3)*'Desinversiones'!$G$6:$G$10*(1+('Desinversiones'!$E$6:$E$10="CRC")*N($F$8)+('Desinversiones'!$E$6:$E$10<>"CRC")*$F$9)^(D41-1)) -> 0 | AE41: =SUM(AB41:AD41) -> 0 | AF41: =AE41 -> 0 | AG41: =AJ40 -> 903739 | AH41: =AG41*$F$13 -> 52934 | AI41: =AA41+AF41 -> 1340 | AJ41: =AG41+AH41+AI41+AM41 -> 958014 | AK41: =AJ41/(1+$F$9)^(D41-1+$F$24/12) -> 622941 | AL41: =IF(AG41<=0,0,MAX(0,-AI41)/AG41) -> 0 | AM41: =MAX(0,-(AG41+AH41+AI41)) -> 0
B42: =B41+1 -> 2038 | C42: =C41+1 -> 58 | D42: =D41+1 -> 13 | E42: =IF(D42<=$F$19,"Acumulación","Retiro") -> Acumulación | F42: =IF(D42<=$P$7,$N$7*12*(1+IF($M$7="CRC",N($F$8),$F$9))^(D42-1),0) -> 113951 | G42: =IF(D42<=$P$8,$N$8*12*(1+IF($M$8="CRC",N($F$8),$F$9))^(D42-1),0) -> 0 | H42: =IF(AND($N$9>0,D42>=$O$9,D42<=$P$9),$N$9*12*(1+IF($M$9="CRC",N($F$8),$F$9))^(D42-1),0) -> 21102 | I42: =SUMPRODUCT(('Ingresos'!$H$14:$H$17>=B42)*'Ingresos'!$G$14:$G$17*(1+('Ingresos'!$E$14:$E$17="CRC")*N($F$8)+('Ingresos'!$E$14:$E$17<>"CRC")*$F$9)^(D42-1))*12 -> 0 | J42: =IF(AND($N$10>0,D42>=N($O$10)),$N$10*12*(1+IF($M$10="CRC",N($F$8),$F$9))^(N($O$10)-1)*(1+N($F$10))^(D42-N($O$10))*IF(D42=N($O$10),IF(AND(ISNUMBER($F$21),N($F$20)>=$C$30),(12-$F$21)/12,1),1),0) -> 0 | K42: ='Pensiones'!T31 -> 0 | L42: ='Pensiones'!U31 -> 0 | M42: =SUM(F42:L42) -> 135053 | N42: =SUMPRODUCT(('Ingresos'!$H$22:$H$26=B42)*'Ingresos'!$G$22:$G$26*(1+('Ingresos'!$E$22:$E$26="CRC")*N($F$8)+('Ingresos'!$E$22:$E$26<>"CRC")*$F$9)^(D42-1)) -> 0 | O42: ='Pensiones'!S31 -> 0 | P42: =SUM(N42:O42) -> 0 | Q42: =M42+P42 -> 135053 | R42: =$W$7*12*(N($F$22)*(1+$F$9)^(D42-1)+(1-N($F$22))*(1+N($F$8))^(D42-1))*IF(D42>$F$19,$F$18,1) -> 104455 | S42: =SUMPRODUCT(('Gastos'!$H$14:$H$17<=B42)*('Gastos'!$H$14:$H$17+'Gastos'!$I$14:$I$17>B42)*'Gastos'!$G$14:$G$17*(1+('Gastos'!$E$14:$E$17="CRC")*N($F$8)+('Gastos'!$E$14:$E$17<>"CRC")*$F$9)^(D42-1)) -> 0 | T42: =$W$10*(1+IF($V$10="CRC",N($F$8),$F$9))^(D42-1) -> 4748 | U42: =(IF(D42<=$X$11,$W$11*12,0)+IF('Gastos'!$G$28="Sí",0,SUMPRODUCT(('Gastos'!$H$22:$H$26>=B42)*'Gastos'!$G$22:$G$26)*12)+SUMPRODUCT(('Gastos'!$H$43:$H$45<=B42)*('Gastos'!$H$43:$H$45+'Gastos'!$I$43:$I$45-1>=B42)*'Gastos'!$K$43:$K$45)) -> 14400 | V42: =SUM(R42:U42) -> 123603 | W42: =SUMPRODUCT(('Gastos'!$I$33:$I$37=1)*('Gastos'!$H$33:$H$37=B42)*'Gastos'!$G$33:$G$37*(1+('Gastos'!$E$33:$E$37="CRC")*N($F$8)+('Gastos'!$E$33:$E$37<>"CRC")*$F$9)^(D42-1))+SUMPRODUCT(('Gastos'!$I$33:$I$37=2)*('Gastos'!$H$33:$H$37<=B42)*'Gastos'!$G$33:$G$37*(1+('Gastos'!$E$33:$E$37="CRC")*N($F$8)+('Gastos'!$E$33:$E$37<>"CRC")*$F$9)^(D42-1))+SUMPRODUCT(('Retiros del portafolio'!$H$15:$H$18=B42)*'Retiros del portafolio'!$G$15:$G$18*(1+('Retiros del portafolio'!$E$15:$E$18="CRC")*N($F$8)+('Retiros del portafolio'!$E$15:$E$18<>"CRC")*$F$9)^(D42-1)) -> 9496 | X42: =SUMPRODUCT(('Retiros del portafolio'!$H$6:$H$9=B42)*'Retiros del portafolio'!$G$6:$G$9*(1+('Retiros del portafolio'!$E$6:$E$9="CRC")*N($F$8)+('Retiros del portafolio'!$E$6:$E$9<>"CRC")*$F$9)^(D42-1)) -> 0 | Y42: =W42+X42 -> 9496 | Z42: =V42+Y42 -> 133099 | AA42: =Q42-Z42 -> 1954 | AB42: =SUMPRODUCT(('Desinversiones'!$H$6:$H$10=B42)*('Desinversiones'!$I$6:$I$10=1)*'Desinversiones'!$G$6:$G$10*(1+('Desinversiones'!$E$6:$E$10="CRC")*N($F$8)+('Desinversiones'!$E$6:$E$10<>"CRC")*$F$9)^(D42-1)) -> 0 | AC42: =SUMPRODUCT(('Desinversiones'!$H$6:$H$10=B42)*('Desinversiones'!$I$6:$I$10=2)*'Desinversiones'!$G$6:$G$10*(1+('Desinversiones'!$E$6:$E$10="CRC")*N($F$8)+('Desinversiones'!$E$6:$E$10<>"CRC")*$F$9)^(D42-1)) -> 0 | AD42: =SUMPRODUCT(('Desinversiones'!$H$6:$H$10=B42)*('Desinversiones'!$I$6:$I$10=3)*'Desinversiones'!$G$6:$G$10*(1+('Desinversiones'!$E$6:$E$10="CRC")*N($F$8)+('Desinversiones'!$E$6:$E$10<>"CRC")*$F$9)^(D42-1)) -> 0 | AE42: =SUM(AB42:AD42) -> 0 | AF42: =AE42 -> 0 | AG42: =AJ41 -> 958014 | AH42: =AG42*$F$13 -> 56113 | AI42: =AA42+AF42 -> 1954 | AJ42: =AG42+AH42+AI42+AM42 -> 1016081 | AK42: =AJ42/(1+$F$9)^(D42-1+$F$24/12) -> 635899 | AL42: =IF(AG42<=0,0,MAX(0,-AI42)/AG42) -> 0 | AM42: =MAX(0,-(AG42+AH42+AI42)) -> 0
... B79: =B78+1 -> 2075 | C79: =C78+1 -> 95 | D79: =D78+1 -> 50 | E79: =IF(D79<=$F$19,"Acumulación","Retiro") -> Retiro | F79: =IF(D79<=$P$7,$N$7*12*(1+IF($M$7="CRC",N($F$8),$F$9))^(D79-1),0) -> 0 | G79: =IF(D79<=$P$8,$N$8*12*(1+IF($M$8="CRC",N($F$8),$F$9))^(D79-1),0) -> 0 | H79: =IF(AND($N$9>0,D79>=$O$9,D79<=$P$9),$N$9*12*(1+IF($M$9="CRC",N($F$8),$F$9))^(D79-1),0) -> 86916 | I79: =SUMPRODUCT(('Ingresos'!$H$14:$H$17>=B79)*'Ingresos'!$G$14:$G$17*(1+('Ingresos'!$E$14:$E$17="CRC")*N($F$8)+('Ingresos'!$E$14:$E$17<>"CRC")*$F$9)^(D79-1))*12 -> 0 | J79: =IF(AND($N$10>0,D79>=N($O$10)),$N$10*12*(1+IF($M$10="CRC",N($F$8),$F$9))^(N($O$10)-1)*(1+N($F$10))^(D79-N($O$10))*IF(D79=N($O$10),IF(AND(ISNUMBER($F$21),N($F$20)>=$C$30),(12-$F$21)/12,1),1),0) -> 59483 | K79: ='Pensiones'!T68 -> 12554 | L79: ='Pensiones'!U68 -> 14740 | M79: =SUM(F79:L79) -> 173694 | N79: =SUMPRODUCT(('Ingresos'!$H$22:$H$26=B79)*'Ingresos'!$G$22:$G$26*(1+('Ingresos'!$E$22:$E$26="CRC")*N($F$8)+('Ingresos'!$E$22:$E$26<>"CRC")*$F$9)^(D79-1)) -> 0 | O79: ='Pensiones'!S68 -> 0 | P79: =SUM(N79:O79) -> 0 | Q79: =M79+P79 -> 173694 | R79: =$W$7*12*(N($F$22)*(1+$F$9)^(D79-1)+(1-N($F$22))*(1+N($F$8))^(D79-1))*IF(D79>$F$19,$F$18,1) -> 430235 | S79: =SUMPRODUCT(('Gastos'!$H$14:$H$17<=B79)*('Gastos'!$H$14:$H$17+'Gastos'!$I$14:$I$17>B79)*'Gastos'!$G$14:$G$17*(1+('Gastos'!$E$14:$E$17="CRC")*N($F$8)+('Gastos'!$E$14:$E$17<>"CRC")*$F$9)^(D79-1)) -> 0 | T79: =$W$10*(1+IF($V$10="CRC",N($F$8),$F$9))^(D79-1) -> 19556 | U79: =(IF(D79<=$X$11,$W$11*12,0)+IF('Gastos'!$G$28="Sí",0,SUMPRODUCT(('Gastos'!$H$22:$H$26>=B79)*'Gastos'!$G$22:$G$26)*12)+SUMPRODUCT(('Gastos'!$H$43:$H$45<=B79)*('Gastos'!$H$43:$H$45+'Gastos'!$I$43:$I$45-1>=B79)*'Gastos'!$K$43:$K$45)) -> 0 | V79: =SUM(R79:U79) -> 449791 | W79: =SUMPRODUCT(('Gastos'!$I$33:$I$37=1)*('Gastos'!$H$33:$H$37=B79)*'Gastos'!$G$33:$G$37*(1+('Gastos'!$E$33:$E$37="CRC")*N($F$8)+('Gastos'!$E$33:$E$37<>"CRC")*$F$9)^(D79-1))+SUMPRODUCT(('Gastos'!$I$33:$I$37=2)*('Gastos'!$H$33:$H$37<=B79)*'Gastos'!$G$33:$G$37*(1+('Gastos'!$E$33:$E$37="CRC")*N($F$8)+('Gastos'!$E$33:$E$37<>"CRC")*$F$9)^(D79-1))+SUMPRODUCT(('Retiros del portafolio'!$H$15:$H$18=B79)*'Retiros del portafolio'!$G$15:$G$18*(1+('Retiros del portafolio'!$E$15:$E$18="CRC")*N($F$8)+('Retiros del portafolio'!$E$15:$E$18<>"CRC")*$F$9)^(D79-1)) -> 39112 | X79: =SUMPRODUCT(('Retiros del portafolio'!$H$6:$H$9=B79)*'Retiros del portafolio'!$G$6:$G$9*(1+('Retiros del portafolio'!$E$6:$E$9="CRC")*N($F$8)+('Retiros del portafolio'!$E$6:$E$9<>"CRC")*$F$9)^(D79-1)) -> 0 | Y79: =W79+X79 -> 39112 | Z79: =V79+Y79 -> 488903 | AA79: =Q79-Z79 -> -315210 | AB79: =SUMPRODUCT(('Desinversiones'!$H$6:$H$10=B79)*('Desinversiones'!$I$6:$I$10=1)*'Desinversiones'!$G$6:$G$10*(1+('Desinversiones'!$E$6:$E$10="CRC")*N($F$8)+('Desinversiones'!$E$6:$E$10<>"CRC")*$F$9)^(D79-1)) -> 0 | AC79: =SUMPRODUCT(('Desinversiones'!$H$6:$H$10=B79)*('Desinversiones'!$I$6:$I$10=2)*'Desinversiones'!$G$6:$G$10*(1+('Desinversiones'!$E$6:$E$10="CRC")*N($F$8)+('Desinversiones'!$E$6:$E$10<>"CRC")*$F$9)^(D79-1)) -> 0 | AD79: =SUMPRODUCT(('Desinversiones'!$H$6:$H$10=B79)*('Desinversiones'!$I$6:$I$10=3)*'Desinversiones'!$G$6:$G$10*(1+('Desinversiones'!$E$6:$E$10="CRC")*N($F$8)+('Desinversiones'!$E$6:$E$10<>"CRC")*$F$9)^(D79-1)) -> 0 | AE79: =SUM(AB79:AD79) -> 0 | AF79: =AE79 -> 0 | AG79: =AJ78 -> 0 | AH79: =AG79*$F$13 -> 0 | AI79: =AA79+AF79 -> -315210 | AJ79: =AG79+AH79+AI79+AM79 -> 0 | AK79: =AJ79/(1+$F$9)^(D79-1+$F$24/12) -> 0 | AL79: =IF(AG79<=0,0,MAX(0,-AI79)/AG79) -> 0 | AM79: =MAX(0,-(AG79+AH79+AI79)) -> 315210
B81: Año (B30) y edad (C30) iniciales: insumos. Flujo neto = ingresos ordinarios + extraordinarios − gastos ordinarios − extraordinarios (las inversiones, es decir las metas pagadas con el portafolio, son salidas). Flujo neto de inversiones = desinversiones (ventas de activos). En el bloque Portafolio, flujo neto = flujo neto (ingresos − gastos) + flujo neto de inversiones: entra al portafolio si es positivo y sale de él si es negativo. Portafolio final = inicial + rendimiento + flujo neto + gasto no cubierto (última columna): no baja de cero; el gasto no cubierto es lo que el portafolio ya no alcanza a pagar. La pensión empieza en el año en que el cliente cumple la edad de pensión (F20), con los meses que siguen a su cumpleaños (F21).

Sheet Ingresos
B1: Ingresos · Cliente de ejemplo
B2: Cada ingreso como lo declaró el cliente: monto y moneda. El tipo de cambio aplicado es el de la celda F7 de la hoja Proyección para los montos en colones (1 para los dólares), y el monto en US$ es el monto declarado entre ese tipo de cambio. La proyección indexa cada monto con la inflación de su moneda: local para los colones e internacional para los dólares. Las celdas en color crema son insumos; las filas libres sirven para agregar elementos.
B4: Ingresos ordinarios · mensuales, en valor de hoy
B5: N.º | C5: Concepto | D5: Monto declarado | E5: Moneda | F5: Tipo de cambio aplicado | G5: Monto en US$ | H5: Desde el período | I5: Hasta el período | J5: Nota
B6: 1 | C6: Ingreso total mensual (actividad) | D6: 2700000 | E6: CRC | F6: =IF(E6="CRC",'Proyección'!$F$7,1) -> 450 | G6: =D6/F6 -> 6000 | H6: 1 | I6: 14 | J6: Hasta la independencia o la edad indicada
B7: 2 | C7: Ingreso mensual de la pareja | D7: 0 | E7: USD | F7: =IF(E7="CRC",'Proyección'!$F$7,1) -> 1 | G7: =D7/F7 -> 0 | H7: 1 | I7: 0 | J7: No aplica
B8: 3 | C8: Otros ingresos recurrentes al mes | D8: 500000 | E8: CRC | F8: =IF(E8="CRC",'Proyección'!$F$7,1) -> 450 | G8: =D8/F8 -> 1111.11 | H8: 5 | I8: 50
B9: Total de ingresos ordinarios al mes (US$) | G9: =SUM(G6:G8) -> 7111.11
B10: Pensiones: la del régimen básico (Pensión del Magisterio), la del ROP y la voluntaria se registran en la hoja «Pensiones»; en la proyección son ingresos ordinarios, cada una en su columna.
B12: Alquileres de inmuebles · mensuales, en valor de hoy
B13: N.º | C13: Inmueble | D13: Alquiler mensual declarado | E13: Moneda | F13: Tipo de cambio aplicado | G13: Monto en US$ | H13: Último año con alquiler | J13: Nota
B14: 1 | C14: Apartamento en Santa Ana | D14: 1100 | E14: USD | F14: =IF(E14="CRC",'Proyección'!$F$7,1) -> 1 | G14: =D14/F14 -> 1100 | H14: 2030 | J14: Hasta el año anterior a la venta
B15: 2 | F15: =IF(E15="CRC",'Proyección'!$F$7,1) -> 1 | G15: =D15/F15 -> 0
B16: 3 | F16: =IF(E16="CRC",'Proyección'!$F$7,1) -> 1 | G16: =D16/F16 -> 0
B17: 4 | F17: =IF(E17="CRC",'Proyección'!$F$7,1) -> 1 | G17: =D17/F17 -> 0
B18: Total de alquileres al mes (US$) | G18: =SUM(G14:G17) -> 1100
B20: Ingresos extraordinarios · en valor de hoy
B21: N.º | C21: Concepto | D21: Monto declarado | E21: Moneda | F21: Tipo de cambio aplicado | G21: Monto en US$ | H21: Año | J21: Nota
B22: 1 | C22: Bono por antigüedad | D22: 40000 | E22: USD | F22: =IF(E22="CRC",'Proyección'!$F$7,1) -> 1 | G22: =D22/F22 -> 40000 | H22: 2028
B23: 2 | C23: Herencia esperada | D23: 120000 | E23: USD | F23: =IF(E23="CRC",'Proyección'!$F$7,1) -> 1 | G23: =D23/F23 -> 120000 | H23: 2032
B24: 3 | F24: =IF(E24="CRC",'Proyección'!$F$7,1) -> 1 | G24: =D24/F24 -> 0
B25: 4 | F25: =IF(E25="CRC",'Proyección'!$F$7,1) -> 1 | G25: =D25/F25 -> 0
B26: 5 | F26: =IF(E26="CRC",'Proyección'!$F$7,1) -> 1 | G26: =D26/F26 -> 0
B27: Total de ingresos extraordinarios (US$) | G27: =SUM(G22:G26) -> 160000
B28: Traslado del FCL: se calcula en la hoja «Pensiones» y entra a la proyección como ingreso extraordinario.
B30: En la proyección · US$ nominales, todo el horizonte
B31: Ingresos ordinarios | G31: ='Proyección'!$AJ$7 -> 5643124
B32: Ingresos extraordinarios | G32: ='Proyección'!$AJ$8 -> 283622
B33: Total de ingresos | G33: ='Proyección'!$AJ$7+'Proyección'!$AJ$8 -> 5926747

Sheet Gastos
B1: Gastos · Cliente de ejemplo
B2: Cada gasto como lo declaró el cliente: monto y moneda. El tipo de cambio aplicado es el de la celda F7 de la hoja Proyección para los montos en colones (1 para los dólares), y el monto en US$ es el monto declarado entre ese tipo de cambio. El gasto familiar y los gastos en colones se indexan con la inflación local; los de dólares, con la internacional. Las cuotas de hipoteca y deudas son fijas. Las celdas en color crema son insumos.
B4: Gastos ordinarios · en valor de hoy
B5: N.º | C5: Concepto | D5: Monto declarado | E5: Moneda | F5: Tipo de cambio aplicado | G5: Monto en US$ | H5: Periodicidad | I5: Hasta el período | J5: Nota
B6: 1 | C6: Gasto familiar mensual | D6: 5500 | E6: USD | F6: =IF(E6="CRC",'Proyección'!$F$7,1) -> 1 | G6: =D6/F6 -> 5500 | H6: Mensual | J6: En el retiro se multiplica por el % de la celda F18 de la hoja Proyección
B7: 2 | C7: Donaciones al año | D7: 3000 | E7: USD | F7: =IF(E7="CRC",'Proyección'!$F$7,1) -> 1 | G7: =D7/F7 -> 3000 | H7: Anual
B8: 3 | C8: Cuota mensual de la hipoteca | D8: 1200 | E8: USD | F8: =IF(E8="CRC",'Proyección'!$F$7,1) -> 1 | G8: =D8/F8 -> 1200 | H8: Mensual | I8: 15 | J8: Hasta el período del plazo restante
B9: Total de gastos ordinarios mensuales (US$) | G9: =SUMIF(H6:H8,"Mensual",G6:G8) -> 6700
B10: Total de gastos ordinarios anuales (US$) | G10: =SUMIF(H6:H8,"Anual",G6:G8) -> 3000
B12: Gastos de dependientes · anuales, en valor de hoy
B13: N.º | C13: Dependiente | D13: Gasto anual declarado | E13: Moneda | F13: Tipo de cambio aplicado | G13: Monto en US$ | H13: Año de inicio | I13: Años que dura | J13: Nota
B14: 1 | C14: Cónyuge o pareja · salud | D14: 12000 | E14: USD | F14: =IF(E14="CRC",'Proyección'!$F$7,1) -> 1 | G14: =D14/F14 -> 12000 | H14: 2030 | I14: 5
B15: 2 | F15: =IF(E15="CRC",'Proyección'!$F$7,1) -> 1 | G15: =D15/F15 -> 0
B16: 3 | F16: =IF(E16="CRC",'Proyección'!$F$7,1) -> 1 | G16: =D16/F16 -> 0
B17: 4 | F17: =IF(E17="CRC",'Proyección'!$F$7,1) -> 1 | G17: =D17/F17 -> 0
B18: Total de gastos de dependientes al año (US$) | G18: =SUM(G14:G17) -> 12000
B20: Deudas · cuotas mensuales y saldos, en valor de hoy
B21: N.º | C21: Deuda | D21: Cuota mensual declarada | E21: Moneda | F21: Tipo de cambio aplicado | G21: Monto en US$ | H21: Último año de pago | I21: Saldo declarado | J21: Moneda del saldo | K21: Saldo en US$ | L21: Tasa anual (informativa)
B22: 1 | C22: Préstamo personal | D22: 157500 | E22: CRC | F22: =IF(E22="CRC",'Proyección'!$F$7,1) -> 450 | G22: =D22/F22 -> 350 | H22: 2029 | I22: 5400000 | J22: CRC | K22: =IF(J22="CRC",I22/'Proyección'!$F$7,N(I22)) -> 12000 | L22: 0.11
B23: 2 | C23: Tarjeta de crédito | D23: 150 | E23: USD | F23: =IF(E23="CRC",'Proyección'!$F$7,1) -> 1 | G23: =D23/F23 -> 150 | H23: 2027 | I23: 3000 | J23: USD | K23: =IF(J23="CRC",I23/'Proyección'!$F$7,N(I23)) -> 3000 | L23: 0.32
B24: 3 | F24: =IF(E24="CRC",'Proyección'!$F$7,1) -> 1 | G24: =D24/F24 -> 0 | K24: =IF(J24="CRC",I24/'Proyección'!$F$7,N(I24)) -> 0
B25: 4 | F25: =IF(E25="CRC",'Proyección'!$F$7,1) -> 1 | G25: =D25/F25 -> 0 | K25: =IF(J25="CRC",I25/'Proyección'!$F$7,N(I25)) -> 0
B26: 5 | F26: =IF(E26="CRC",'Proyección'!$F$7,1) -> 1 | G26: =D26/F26 -> 0 | K26: =IF(J26="CRC",I26/'Proyección'!$F$7,N(I26)) -> 0
B27: Total de cuotas al mes y de saldos (US$) | G27: =SUM(G22:G26) -> 500 | K27: =SUM(K22:K26) -> 15000
B28: ¿Las cuotas ya están incluidas en el gasto familiar? (Sí o No) | G28: No
B29: Si las cuotas ya están incluidas en el gasto familiar (pregunta de deudas), se muestran solo como información y no se suman de nuevo. El saldo es informativo: la proyección paga la cuota mensual hasta el último año de pago. La tasa no entra al cálculo.
B31: Gastos extraordinarios · en valor de hoy
B32: N.º | C32: Gasto | D32: Monto declarado | E32: Moneda | F32: Tipo de cambio aplicado | G32: Monto en US$ | H32: Año | I32: Frecuencia (1 una vez · 2 cada año) | J32: Nota
B33: 1 | C33: Seguro y marchamo de vehículos | D33: 6000 | E33: USD | F33: =IF(E33="CRC",'Proyección'!$F$7,1) -> 1 | G33: =D33/F33 -> 6000 | H33: 2027 | I33: 2 | J33: Cada año desde el año indicado
B34: 2 | C34: Remodelación de la casa | D34: 15750000 | E34: CRC | F34: =IF(E34="CRC",'Proyección'!$F$7,1) -> 450 | G34: =D34/F34 -> 35000 | H34: 2030 | I34: 1 | J34: Una sola vez
B35: 3 | F35: =IF(E35="CRC",'Proyección'!$F$7,1) -> 1 | G35: =D35/F35 -> 0
B36: 4 | F36: =IF(E36="CRC",'Proyección'!$F$7,1) -> 1 | G36: =D36/F36 -> 0
B37: 5 | F37: =IF(E37="CRC",'Proyección'!$F$7,1) -> 1 | G37: =D37/F37 -> 0
B38: Total de gastos extraordinarios (US$) | G38: =SUM(G33:G37) -> 41000
B39: Las metas pagadas con el portafolio y los retiros adicionales están en la hoja «Retiros del portafolio»; en la proyección van con los gastos extraordinarios (columnas Gastos extraordinarios e Inversiones).
B41: Metas financiadas con crédito · cuota anual, desde el año de la meta
B42: N.º | C42: Meta | D42: Monto declarado | E42: Moneda | F42: Tipo de cambio aplicado | G42: Monto en US$ | H42: Año de la meta | I42: Plazo (años) | J42: Tasa anual | K42: Cuota anual (US$)
B43: 1 | F43: =IF(E43="CRC",'Proyección'!$F$7,1) -> 1 | G43: =D43/F43 -> 0 | K43: =IF(OR(G43=0,N(I43)=0),0,PMT(N(J43),I43,-G43*(1+IF(E43="CRC",N('Proyección'!$F$8),'Proyección'!$F$9))^(H43-'Proyección'!$B$30))) -> 0
B44: 2 | F44: =IF(E44="CRC",'Proyección'!$F$7,1) -> 1 | G44: =D44/F44 -> 0 | K44: =IF(OR(G44=0,N(I44)=0),0,PMT(N(J44),I44,-G44*(1+IF(E44="CRC",N('Proyección'!$F$8),'Proyección'!$F$9))^(H44-'Proyección'!$B$30))) -> 0
B45: 3 | F45: =IF(E45="CRC",'Proyección'!$F$7,1) -> 1 | G45: =D45/F45 -> 0 | K45: =IF(OR(G45=0,N(I45)=0),0,PMT(N(J45),I45,-G45*(1+IF(E45="CRC",N('Proyección'!$F$8),'Proyección'!$F$9))^(H45-'Proyección'!$B$30))) -> 0
B46: Total de cuotas anuales de crédito (US$) | K46: =SUM(K43:K45) -> 0
B47: La cuota se paga cada año desde el año de la meta y durante el plazo del crédito, y se suma a las cuotas de hipoteca y deudas de la hoja Proyección. La tasa y el plazo son insumos: al cambiarlos, la proyección se recalcula.
B49: En la proyección · US$ nominales, todo el horizonte
B50: Gastos ordinarios | G50: =-'Proyección'!$AJ$9 -> 10458610
B51: Gastos extraordinarios | G51: =-'Proyección'!$AJ$10 -> 1031906
B52: Total de gastos | G52: =-'Proyección'!$AJ$9-'Proyección'!$AJ$10 -> 11490516

Sheet Inversiones
B1: Inversiones · Cliente de ejemplo
B2: El portafolio de inversión con el que inicia la proyección, como lo declaró el cliente (monto y moneda), y lo que se invierte en él durante la proyección. Abajo, las demás inversiones del patrimonio, solo como información: no entran a la proyección salvo cuando el cliente prevé venderlas (hoja «Desinversiones»).
B4: Portafolio de inversión · en valor de hoy
B5: N.º | C5: Concepto | D5: Monto declarado | E5: Moneda | F5: Tipo de cambio aplicado | G5: Monto en US$ | H5: Nota
B6: 1 | C6: Capital inicial del portafolio | D6: 250000 | E6: USD | F6: =IF(E6="CRC",'Proyección'!$F$7,1) -> 1 | G6: =D6/F6 -> 250000 | H6: Inversiones líquidas que administra la firma
B7: Rendimiento esperado del portafolio | G7: ='Proyección'!$F$13 -> 0.0585725 | H7: Según el perfil de riesgo; se ajusta en la hoja Proyección (F13)
B9: En la proyección · US$ nominales, todo el horizonte
B10: Capital inicial | G10: ='Proyección'!$AO$7 -> 250000
B11: Rendimientos del portafolio | G11: ='Proyección'!$AO$10 -> 1310831
B13: Otras inversiones del patrimonio · informativo, en valor de hoy
B14: N.º | C14: Inversión | D14: Valor declarado | E14: Moneda | F14: Tipo de cambio aplicado | G14: Monto en US$ | H14: Participación | I14: Valor según la participación (US$) | J14: Nota
B15: 1 | C15: Inmueble: Apartamento en Santa Ana | D15: 180000 | E15: USD | F15: =IF(E15="CRC",'Proyección'!$F$7,1) -> 1 | G15: =D15/F15 -> 180000 | I15: =G15*IF(H15="",1,H15) -> 180000
B16: 2 | C16: Empresa: EMPRESA | D16: 900000 | E16: USD | F16: =IF(E16="CRC",'Proyección'!$F$7,1) -> 1 | G16: =D16/F16 -> 900000 | H16: 1 | I16: =G16*IF(H16="",1,H16) -> 900000
B17: 3 | C17: Capital privado | D17: 800000 | E17: USD | F17: =IF(E17="CRC",'Proyección'!$F$7,1) -> 1 | G17: =D17/F17 -> 800000 | H17: 0.15 | I17: =G17*IF(H17="",1,H17) -> 120000
B18: 4 | C18: ROP (saldo) | D18: 12000000 | E18: CRC | F18: =IF(E18="CRC",'Proyección'!$F$7,1) -> 450 | G18: =D18/F18 -> 26666.67 | I18: =G18*IF(H18="",1,H18) -> 26666.67 | J18: Su evolución está en la hoja «Pensiones»
B19: 5 | C19: FCL (saldo) | D19: 12000000 | E19: CRC | F19: =IF(E19="CRC",'Proyección'!$F$7,1) -> 450 | G19: =D19/F19 -> 26666.67 | I19: =G19*IF(H19="",1,H19) -> 26666.67 | J19: Su evolución está en la hoja «Pensiones»
B20: 6 | C20: Pensión voluntaria (saldo) | D20: 12000000 | E20: CRC | F20: =IF(E20="CRC",'Proyección'!$F$7,1) -> 450 | G20: =D20/F20 -> 26666.67 | I20: =G20*IF(H20="",1,H20) -> 26666.67 | J20: Su evolución está en la hoja «Pensiones»
B21: 7 | F21: =IF(E21="CRC",'Proyección'!$F$7,1) -> 1 | G21: =D21/F21 -> 0 | I21: =G21*IF(H21="",1,H21) -> 0
B22: 8 | F22: =IF(E22="CRC",'Proyección'!$F$7,1) -> 1 | G22: =D22/F22 -> 0 | I22: =G22*IF(H22="",1,H22) -> 0
B23: 9 | F23: =IF(E23="CRC",'Proyección'!$F$7,1) -> 1 | G23: =D23/F23 -> 0 | I23: =G23*IF(H23="",1,H23) -> 0
B24: Total de otras inversiones (US$) | I24: =SUM(I15:I23) -> 1280000

Sheet Desinversiones
B1: Desinversiones · Cliente de ejemplo
B2: Las ventas de activos que entran al portafolio, como las declaró el cliente: monto y moneda, con el tipo de cambio aplicado (celda F7 de la hoja Proyección para los colones, 1 para los dólares) y el monto en US$. Cada monto se indexa con la inflación de su moneda hasta su año. Su total es el flujo neto de inversiones de la proyección. Las celdas en color crema son insumos.
B4: Venta de activos · monto que entra al portafolio, en valor de hoy
B5: N.º | C5: Activo | D5: Monto que entra (declarado) | E5: Moneda | F5: Tipo de cambio aplicado | G5: Monto en US$ | H5: Año de la venta | I5: Tipo (1 inmueble · 2 empresa · 3 otro) | J5: Nota
B6: 1 | C6: Venta del inmueble 1 | D6: 180000 | E6: USD | F6: =IF(E6="CRC",'Proyección'!$F$7,1) -> 1 | G6: =D6/F6 -> 180000 | H6: 2031 | I6: 1
B7: 2 | C7: Venta de un lote | D7: 150000 | E7: USD | F7: =IF(E7="CRC",'Proyección'!$F$7,1) -> 1 | G7: =D7/F7 -> 150000 | H7: 2033 | I7: 3
B8: 3 | F8: =IF(E8="CRC",'Proyección'!$F$7,1) -> 1 | G8: =D8/F8 -> 0
B9: 4 | F9: =IF(E9="CRC",'Proyección'!$F$7,1) -> 1 | G9: =D9/F9 -> 0
B10: 5 | F10: =IF(E10="CRC",'Proyección'!$F$7,1) -> 1 | G10: =D10/F10 -> 0
B11: Total de venta de inmuebles (US$) | G11: =SUMIF(I6:I10,1,G6:G10) -> 180000
B12: Total de venta de la empresa (US$) | G12: =SUMIF(I6:I10,2,G6:G10) -> 0
B13: Total de venta de otros activos (US$) | G13: =SUMIF(I6:I10,3,G6:G10) -> 150000
B14: Total de desinversiones (US$) | G14: =SUM(G6:G10) -> 330000
B16: En la proyección · US$ nominales, todo el horizonte
B17: Flujo neto de inversiones (desinversiones) | G17: ='Proyección'!$AO$9 -> 414012

Sheet Retiros del portafolio
B1: Retiros del portafolio · Cliente de ejemplo
B2: Las salidas de dinero del portafolio que declaró el cliente: las metas que paga con el portafolio y los retiros adicionales, cada uno con su monto y moneda, el tipo de cambio aplicado (celda F7 de la hoja Proyección para los colones, 1 para los dólares) y el monto en US$. Cada monto se indexa con la inflación de su moneda hasta su año. En la proyección, las metas van en la columna Inversiones y los retiros adicionales en la de Gastos extraordinarios. Las celdas en color crema son insumos.
B4: Metas pagadas con el portafolio · en valor de hoy
B5: N.º | C5: Meta | D5: Monto declarado | E5: Moneda | F5: Tipo de cambio aplicado | G5: Monto en US$ | H5: Año | J5: Prioridad
B6: 1 | C6: Vivienda o propiedad | D6: 40000 | E6: USD | F6: =IF(E6="CRC",'Proyección'!$F$7,1) -> 1 | G6: =D6/F6 -> 40000 | H6: 2031 | J6: Deseable
B7: 2 | F7: =IF(E7="CRC",'Proyección'!$F$7,1) -> 1 | G7: =D7/F7 -> 0
B8: 3 | F8: =IF(E8="CRC",'Proyección'!$F$7,1) -> 1 | G8: =D8/F8 -> 0
B9: 4 | F9: =IF(E9="CRC",'Proyección'!$F$7,1) -> 1 | G9: =D9/F9 -> 0
B10: Total de metas pagadas con el portafolio (US$) | G10: =SUM(G6:G9) -> 40000
B11: Las metas financiadas con crédito no salen del portafolio: su cuota anual está en la hoja «Gastos».
B13: Retiros adicionales del portafolio · en valor de hoy
B14: N.º | C14: Motivo del retiro | D14: Monto declarado | E14: Moneda | F14: Tipo de cambio aplicado | G14: Monto en US$ | H14: Año | J14: Nota
B15: 1 | C15: Retiro del portafolio | D15: 50000 | E15: USD | F15: =IF(E15="CRC",'Proyección'!$F$7,1) -> 1 | G15: =D15/F15 -> 50000 | H15: 2031 | J15: Una sola vez, en su año
B16: 2 | F16: =IF(E16="CRC",'Proyección'!$F$7,1) -> 1 | G16: =D16/F16 -> 0
B17: 3 | F17: =IF(E17="CRC",'Proyección'!$F$7,1) -> 1 | G17: =D17/F17 -> 0
B18: 4 | F18: =IF(E18="CRC",'Proyección'!$F$7,1) -> 1 | G18: =D18/F18 -> 0
B19: Total de retiros adicionales (US$) | G19: =SUM(G15:G18) -> 50000
B21: En la proyección · US$ nominales, todo el horizonte
B22: Metas pagadas con el portafolio (columna Inversiones) | G22: =SUM('Proyección'!$X$30:$X$79) -> 48433
B23: Retiros adicionales (en la columna Gastos extraordinarios) | G23: 60541
B24: Total de retiros del portafolio | G24: =SUM(G22:G23) -> 108973

Sheet Pensiones
B1: Pensiones
B2: Todas las pensiones del cliente. Arriba a la derecha, la pensión del régimen básico (IVM u otro). Abajo, ROP, FCL y pensión voluntaria, en dólares, con las reglas de la Ley de Protección al Trabajador (n.º 7983). El ROP se recibe como pensión mensual desde el año en que el cliente cumple la edad de pensión (Proyección F20), según su modalidad, o en un solo pago a los 65 años si no hay pensión de un régimen básico. La pensión voluntaria es un ingreso ordinario desde la misma edad, con la modalidad del ROP. El primer año se pagan solo los meses después del cumpleaños (mes de nacimiento en Proyección F21). Los aportes terminan al empezar la pensión del fondo o en la independencia. El FCL se traslada completo en cada quinquenio o al terminar la relación laboral. Las celdas de insumos pueden modificarse.
B4: Supuestos | G4: Pensión del régimen básico · mensual, en valor de hoy
B5: Rendimiento anual de los fondos (Proyección F14) | E5: =N('Proyección'!$F$14) -> 0.06 | G5: Concepto | H5: Monto mensual declarado | I5: Moneda | J5: Tipo de cambio aplicado | K5: Monto en US$ | L5: Desde el período | M5: Nota
B6: Crecimiento de los aportes al ROP y al FCL (Proyección F11) | E6: =N('Proyección'!$F$11) -> 0.039 | G6: Pensión del Magisterio (mensual) | H6: 800000 | I6: CRC | J6: =IF(I6="CRC",'Proyección'!$F$7,1) -> 450 | K6: =H6/J6 -> 1777.78 | L6: =MAX(1,N('Proyección'!$F$20)-'Proyección'!$C$30+1) -> 20 | M6: =IF(AND(ISNUMBER('Proyección'!$F$21),N('Proyección'!$F$20)>='Proyección'!$C$30),"Desde el año en que cumple "&'Proyección'!$F$20&" años; ese año, "&(12-'Proyección'!$F$21)&" meses","Desde el año en que cumple "&'Proyección'!$F$20&" años") -> Desde el año en que cumple 65 años; ese año, 7 meses
B7: Años de aportes, hasta la independencia (Proyección F19) | E7: ='Proyección'!$F$19 -> 14 | G7: La proyección la toma de aquí (columna de la pensión en la hoja Proyección), con la inflación de la pensión (Proyección F10). La del ROP y la voluntaria están en la evolución anual de abajo.
B8: Período de la independencia financiera | E8: =E7+1 -> 15
B9: Edad actual del cliente | E9: ='Proyección'!$C$30 -> 46
B10: Crecimiento de los aportes a la pensión voluntaria (Proyección F12) | E10: =N('Proyección'!$F$12) -> 0.039
B11: Fondo | C11: Saldo actual (US$) | D11: Aporte mensual (US$) | E11: Origen del aporte | F11: Período de traslado o de inicio de la pensión | G11: Año | H11: Regla de la ley | I11: Edad final de la renta | J11: Aportes acumulados | K11: Rendimientos acumulados | L11: Trasladado al portafolio | M11: Pensión pagada | N11: Saldo declarado | O11: Moneda del saldo | P11: Aporte declarado | Q11: Moneda del aporte
B12: ROP | C12: =IF(O12="CRC",N12/'Proyección'!$F$7,N12) -> 26666.667 | D12: ='Proyección'!$N$7*N('Proyección'!$F$15) -> 255 | E12: Estimado: 4.25% del salario (Proyección F15) | F12: =MAX(1,N('Proyección'!$F$20)-$E$9+1) -> 20 | G12: ='Proyección'!$B$30+F12-1 -> 2045 | H12: Pensión mensual: retiro programado | I12: 100 | J12: =SUM(E19:E68) -> 53296 | K12: =SUM(F19:F68) -> 356655 | L12: 0 | M12: =SUM(G19:G68) -> 383735 | N12: 12000000 | O12: CRC
B13: FCL | C13: =IF(O13="CRC",N13/'Proyección'!$F$7,N13) -> 26666.667 | D13: ='Proyección'!$N$7*N('Proyección'!$F$16) -> 90 | E13: Estimado: 1.5% del salario (Proyección F16) | F13: =$E$8 -> 15 | G13: ='Proyección'!$B$30+F13-1 -> 2040 | H13: Al terminar la relación laboral | J13: =SUM(J19:J68) -> 18810 | K13: =SUM(K19:K68) -> 44000 | L13: =SUM(L19:L68) -> 89477 | M13: 0 | N13: 12000000 | O13: CRC
B14: Pensión voluntaria | C14: =IF(O14="CRC",N14/'Proyección'!$F$7,N14) -> 26666.667 | D14: =IF(Q14="CRC",P14/'Proyección'!$F$7,P14) -> 333.33333 | E14: Declarado por el cliente | F14: =MAX(1,N('Proyección'!$F$20)-$E$9+1) -> 20 | G14: ='Proyección'!$B$30+F14-1 -> 2045 | H14: Pensión mensual: retiro programado (la que eligió para el ROP) | I14: 100 | J14: =SUM(O19:O68) -> 69668 | K14: =SUM(P19:P68) -> 416331 | L14: 0 | M14: =SUM(Q19:Q68) -> 450573 | N14: 12000000 | O14: CRC | P14: 150000 | Q14: CRC
B17: Evolución anual | D17: ROP | I17: FCL | N17: Pensión voluntaria | S17: Total
B18: Período | C18: Año | D18: Saldo inicial | E18: Aportes | F18: Rendimiento | G18: Pensión pagada | H18: Saldo final | I18: Saldo inicial | J18: Aportes | K18: Rendimiento | L18: Traslado al portafolio | M18: Saldo final | N18: Saldo inicial | O18: Aportes | P18: Rendimiento | Q18: Pensión pagada | R18: Saldo final | S18: Traslado total al portafolio | T18: Pensión del ROP | U18: Pensión voluntaria
B19: 1 | C19: ='Proyección'!B30 -> 2026 | D19: =C12 -> 26667 | E19: =IF(AND(B19<=$E$7,B19<$F$12),$D$12*12*(1+$E$6)^(B19-1),0)*'Proyección'!$F$24/12 -> 765 | F19: =D19*$E$5*'Proyección'!$F$24/12 -> 400 | G19: =IF(B19>=$F$12,IF(($I$12-$E$9-B19+2)<=1,D19+F19,IF($E$5=0,D19/($I$12-$E$9-B19+2),D19*$E$5/(1-(1+$E$5)^(-($I$12-$E$9-B19+2))))*MIN(IF(AND(B19=$F$12,ISNUMBER('Proyección'!$F$21),N('Proyección'!$F$20)>=$E$9),(12-'Proyección'!$F$21)/12,1),'Proyección'!$F$24/12)),0) -> 0 | H19: =D19+E19+F19-G19 -> 27832 | I19: =C13 -> 26667 | J19: =IF(AND(B19<=$E$7),$D$13*12*(1+$E$6)^(B19-1),0)*'Proyección'!$F$24/12 -> 270 | K19: =I19*$E$5*'Proyección'!$F$24/12 -> 400 | L19: =IF(OR(B19=$F$13,B19=$E$8,B19=50),I19+J19+K19,0) -> 0 | M19: =I19+J19+K19-L19 -> 27337 | N19: =C14 -> 26667 | O19: =IF(AND(B19<=$E$7,B19<$F$14),$D$14*12*(1+$E$10)^(B19-1),0)*'Proyección'!$F$24/12 -> 1000 | P19: =N19*$E$5*'Proyección'!$F$24/12 -> 400 | Q19: =IF(B19>=$F$14,IF(($I$14-$E$9-B19+2)<=1,N19+P19,IF($E$5=0,N19/($I$14-$E$9-B19+2),N19*$E$5/(1-(1+$E$5)^(-($I$14-$E$9-B19+2))))*MIN(IF(AND(B19=$F$14,ISNUMBER('Proyección'!$F$21),N('Proyección'!$F$20)>=$E$9),(12-'Proyección'!$F$21)/12,1),'Proyección'!$F$24/12)),0) -> 0 | R19: =N19+O19+P19-Q19 -> 28067 | S19: =L19 -> 0 | T19: =G19 -> 0 | U19: =Q19 -> 0
B20: 2 | C20: ='Proyección'!B31 -> 2027 | D20: =H19 -> 27832 | E20: =IF(AND(B20<=$E$7,B20<$F$12),$D$12*12*(1+$E$6)^(B20-1),0) -> 3179 | F20: =D20*$E$5 -> 1670 | G20: =IF(B20>=$F$12,IF(($I$12-$E$9-B20+2)<=1,D20+F20,IF($E$5=0,D20/($I$12-$E$9-B20+2),D20*$E$5/(1-(1+$E$5)^(-($I$12-$E$9-B20+2))))*IF(AND(B20=$F$12,ISNUMBER('Proyección'!$F$21),N('Proyección'!$F$20)>=$E$9),(12-'Proyección'!$F$21)/12,1)),0) -> 0 | H20: =D20+E20+F20-G20 -> 32681 | I20: =M19 -> 27337 | J20: =IF(AND(B20<=$E$7),$D$13*12*(1+$E$6)^(B20-1),0) -> 1122 | K20: =I20*$E$5 -> 1640 | L20: =IF(OR(B20=$F$13,B20=$E$8,B20=50),I20+J20+K20,0) -> 0 | M20: =I20+J20+K20-L20 -> 30099 | N20: =R19 -> 28067 | O20: =IF(AND(B20<=$E$7,B20<$F$14),$D$14*12*(1+$E$10)^(B20-1),0) -> 4156 | P20: =N20*$E$5 -> 1684 | Q20: =IF(B20>=$F$14,IF(($I$14-$E$9-B20+2)<=1,N20+P20,IF($E$5=0,N20/($I$14-$E$9-B20+2),N20*$E$5/(1-(1+$E$5)^(-($I$14-$E$9-B20+2))))*IF(AND(B20=$F$14,ISNUMBER('Proyección'!$F$21),N('Proyección'!$F$20)>=$E$9),(12-'Proyección'!$F$21)/12,1)),0) -> 0 | R20: =N20+O20+P20-Q20 -> 33907 | S20: =L20 -> 0 | T20: =G20 -> 0 | U20: =Q20 -> 0
B21: 3 | C21: ='Proyección'!B32 -> 2028 | D21: =H20 -> 32681 | E21: =IF(AND(B21<=$E$7,B21<$F$12),$D$12*12*(1+$E$6)^(B21-1),0) -> 3303 | F21: =D21*$E$5 -> 1961 | G21: =IF(B21>=$F$12,IF(($I$12-$E$9-B21+2)<=1,D21+F21,IF($E$5=0,D21/($I$12-$E$9-B21+2),D21*$E$5/(1-(1+$E$5)^(-($I$12-$E$9-B21+2))))*IF(AND(B21=$F$12,ISNUMBER('Proyección'!$F$21),N('Proyección'!$F$20)>=$E$9),(12-'Proyección'!$F$21)/12,1)),0) -> 0 | H21: =D21+E21+F21-G21 -> 37945 | I21: =M20 -> 30099 | J21: =IF(AND(B21<=$E$7),$D$13*12*(1+$E$6)^(B21-1),0) -> 1166 | K21: =I21*$E$5 -> 1806 | L21: =IF(OR(B21=$F$13,B21=$E$8,B21=50),I21+J21+K21,0) -> 0 | M21: =I21+J21+K21-L21 -> 33071 | N21: =R20 -> 33907 | O21: =IF(AND(B21<=$E$7,B21<$F$14),$D$14*12*(1+$E$10)^(B21-1),0) -> 4318 | P21: =N21*$E$5 -> 2034 | Q21: =IF(B21>=$F$14,IF(($I$14-$E$9-B21+2)<=1,N21+P21,IF($E$5=0,N21/($I$14-$E$9-B21+2),N21*$E$5/(1-(1+$E$5)^(-($I$14-$E$9-B21+2))))*IF(AND(B21=$F$14,ISNUMBER('Proyección'!$F$21),N('Proyección'!$F$20)>=$E$9),(12-'Proyección'!$F$21)/12,1)),0) -> 0 | R21: =N21+O21+P21-Q21 -> 40259 | S21: =L21 -> 0 | T21: =G21 -> 0 | U21: =Q21 -> 0
B22: 4 | C22: ='Proyección'!B33 -> 2029 | D22: =H21 -> 37945 | E22: =IF(AND(B22<=$E$7,B22<$F$12),$D$12*12*(1+$E$6)^(B22-1),0) -> 3432 | F22: =D22*$E$5 -> 2277 | G22: =IF(B22>=$F$12,IF(($I$12-$E$9-B22+2)<=1,D22+F22,IF($E$5=0,D22/($I$12-$E$9-B22+2),D22*$E$5/(1-(1+$E$5)^(-($I$12-$E$9-B22+2))))*IF(AND(B22=$F$12,ISNUMBER('Proyección'!$F$21),N('Proyección'!$F$20)>=$E$9),(12-'Proyección'!$F$21)/12,1)),0) -> 0 | H22: =D22+E22+F22-G22 -> 43654 | I22: =M21 -> 33071 | J22: =IF(AND(B22<=$E$7),$D$13*12*(1+$E$6)^(B22-1),0) -> 1211 | K22: =I22*$E$5 -> 1984 | L22: =IF(OR(B22=$F$13,B22=$E$8,B22=50),I22+J22+K22,0) -> 0 | M22: =I22+J22+K22-L22 -> 36266 | N22: =R21 -> 40259 | O22: =IF(AND(B22<=$E$7,B22<$F$14),$D$14*12*(1+$E$10)^(B22-1),0) -> 4486 | P22: =N22*$E$5 -> 2416 | Q22: =IF(B22>=$F$14,IF(($I$14-$E$9-B22+2)<=1,N22+P22,IF($E$5=0,N22/($I$14-$E$9-B22+2),N22*$E$5/(1-(1+$E$5)^(-($I$14-$E$9-B22+2))))*IF(AND(B22=$F$14,ISNUMBER('Proyección'!$F$21),N('Proyección'!$F$20)>=$E$9),(12-'Proyección'!$F$21)/12,1)),0) -> 0 | R22: =N22+O22+P22-Q22 -> 47161 | S22: =L22 -> 0 | T22: =G22 -> 0 | U22: =Q22 -> 0
B23: 5 | C23: ='Proyección'!B34 -> 2030 | D23: =H22 -> 43654 | E23: =IF(AND(B23<=$E$7,B23<$F$12),$D$12*12*(1+$E$6)^(B23-1),0) -> 3566 | F23: =D23*$E$5 -> 2619 | G23: =IF(B23>=$F$12,IF(($I$12-$E$9-B23+2)<=1,D23+F23,IF($E$5=0,D23/($I$12-$E$9-B23+2),D23*$E$5/(1-(1+$E$5)^(-($I$12-$E$9-B23+2))))*IF(AND(B23=$F$12,ISNUMBER('Proyección'!$F$21),N('Proyección'!$F$20)>=$E$9),(12-'Proyección'!$F$21)/12,1)),0) -> 0 | H23: =D23+E23+F23-G23 -> 49839 | I23: =M22 -> 36266 | J23: =IF(AND(B23<=$E$7),$D$13*12*(1+$E$6)^(B23-1),0) -> 1259 | K23: =I23*$E$5 -> 2176 | L23: =IF(OR(B23=$F$13,B23=$E$8,B23=50),I23+J23+K23,0) -> 0 | M23: =I23+J23+K23-L23 -> 39701 | N23: =R22 -> 47161 | O23: =IF(AND(B23<=$E$7,B23<$F$14),$D$14*12*(1+$E$10)^(B23-1),0) -> 4661 | P23: =N23*$E$5 -> 2830 | Q23: =IF(B23>=$F$14,IF(($I$14-$E$9-B23+2)<=1,N23+P23,IF($E$5=0,N23/($I$14-$E$9-B23+2),N23*$E$5/(1-(1+$E$5)^(-($I$14-$E$9-B23+2))))*IF(AND(B23=$F$14,ISNUMBER('Proyección'!$F$21),N('Proyección'!$F$20)>=$E$9),(12-'Proyección'!$F$21)/12,1)),0) -> 0 | R23: =N23+O23+P23-Q23 -> 54652 | S23: =L23 -> 0 | T23: =G23 -> 0 | U23: =Q23 -> 0
B24: 6 | C24: ='Proyección'!B35 -> 2031 | D24: =H23 -> 49839 | E24: =IF(AND(B24<=$E$7,B24<$F$12),$D$12*12*(1+$E$6)^(B24-1),0) -> 3705 | F24: =D24*$E$5 -> 2990 | G24: =IF(B24>=$F$12,IF(($I$12-$E$9-B24+2)<=1,D24+F24,IF($E$5=0,D24/($I$12-$E$9-B24+2),D24*$E$5/(1-(1+$E$5)^(-($I$12-$E$9-B24+2))))*IF(AND(B24=$F$12,ISNUMBER('Proyección'!$F$21),N('Proyección'!$F$20)>=$E$9),(12-'Proyección'!$F$21)/12,1)),0) -> 0 | H24: =D24+E24+F24-G24 -> 56535 | I24: =M23 -> 39701 | J24: =IF(AND(B24<=$E$7),$D$13*12*(1+$E$6)^(B24-1),0) -> 1308 | K24: =I24*$E$5 -> 2382 | L24: =IF(OR(B24=$F$13,B24=$E$8,B24=50),I24+J24+K24,0) -> 0 | M24: =I24+J24+K24-L24 -> 43391 | N24: =R23 -> 54652 | O24: =IF(AND(B24<=$E$7,B24<$F$14),$D$14*12*(1+$E$10)^(B24-1),0) -> 4843 | P24: =N24*$E$5 -> 3279 | Q24: =IF(B24>=$F$14,IF(($I$14-$E$9-B24+2)<=1,N24+P24,IF($E$5=0,N24/($I$14-$E$9-B24+2),N24*$E$5/(1-(1+$E$5)^(-($I$14-$E$9-B24+2))))*IF(AND(B24=$F$14,ISNUMBER('Proyección'!$F$21),N('Proyección'!$F$20)>=$E$9),(12-'Proyección'!$F$21)/12,1)),0) -> 0 | R24: =N24+O24+P24-Q24 -> 62775 | S24: =L24 -> 0 | T24: =G24 -> 0 | U24: =Q24 -> 0
B25: 7 | C25: ='Proyección'!B36 -> 2032 | D25: =H24 -> 56535 | E25: =IF(AND(B25<=$E$7,B25<$F$12),$D$12*12*(1+$E$6)^(B25-1),0) -> 3850 | F25: =D25*$E$5 -> 3392 | G25: =IF(B25>=$F$12,IF(($I$12-$E$9-B25+2)<=1,D25+F25,IF($E$5=0,D25/($I$12-$E$9-B25+2),D25*$E$5/(1-(1+$E$5)^(-($I$12-$E$9-B25+2))))*IF(AND(B25=$F$12,ISNUMBER('Proyección'!$F$21),N('Proyección'!$F$20)>=$E$9),(12-'Proyección'!$F$21)/12,1)),0) -> 0 | H25: =D25+E25+F25-G25 -> 63776 | I25: =M24 -> 43391 | J25: =IF(AND(B25<=$E$7),$D$13*12*(1+$E$6)^(B25-1),0) -> 1359 | K25: =I25*$E$5 -> 2603 | L25: =IF(OR(B25=$F$13,B25=$E$8,B25=50),I25+J25+K25,0) -> 0 | M25: =I25+J25+K25-L25 -> 47353 | N25: =R24 -> 62775 | O25: =IF(AND(B25<=$E$7,B25<$F$14),$D$14*12*(1+$E$10)^(B25-1),0) -> 5032 | P25: =N25*$E$5 -> 3766 | Q25: =IF(B25>=$F$14,IF(($I$14-$E$9-B25+2)<=1,N25+P25,IF($E$5=0,N25/($I$14-$E$9-B25+2),N25*$E$5/(1-(1+$E$5)^(-($I$14-$E$9-B25+2))))*IF(AND(B25=$F$14,ISNUMBER('Proyección'!$F$21),N('Proyección'!$F$20)>=$E$9),(12-'Proyección'!$F$21)/12,1)),0) -> 0 | R25: =N25+O25+P25-Q25 -> 71573 | S25: =L25 -> 0 | T25: =G25 -> 0 | U25: =Q25 -> 0
B26: 8 | C26: ='Proyección'!B37 -> 2033 | D26: =H25 -> 63776 | E26: =IF(AND(B26<=$E$7,B26<$F$12),$D$12*12*(1+$E$6)^(B26-1),0) -> 4000 | F26: =D26*$E$5 -> 3827 | G26: =IF(B26>=$F$12,IF(($I$12-$E$9-B26+2)<=1,D26+F26,IF($E$5=0,D26/($I$12-$E$9-B26+2),D26*$E$5/(1-(1+$E$5)^(-($I$12-$E$9-B26+2))))*IF(AND(B26=$F$12,ISNUMBER('Proyección'!$F$21),N('Proyección'!$F$20)>=$E$9),(12-'Proyección'!$F$21)/12,1)),0) -> 0 | H26: =D26+E26+F26-G26 -> 71603 | I26: =M25 -> 47353 | J26: =IF(AND(B26<=$E$7),$D$13*12*(1+$E$6)^(B26-1),0) -> 1412 | K26: =I26*$E$5 -> 2841 | L26: =IF(OR(B26=$F$13,B26=$E$8,B26=50),I26+J26+K26,0) -> 0 | M26: =I26+J26+K26-L26 -> 51606 | N26: =R25 -> 71573 | O26: =IF(AND(B26<=$E$7,B26<$F$14),$D$14*12*(1+$E$10)^(B26-1),0) -> 5228 | P26: =N26*$E$5 -> 4294 | Q26: =IF(B26>=$F$14,IF(($I$14-$E$9-B26+2)<=1,N26+P26,IF($E$5=0,N26/($I$14-$E$9-B26+2),N26*$E$5/(1-(1+$E$5)^(-($I$14-$E$9-B26+2))))*IF(AND(B26=$F$14,ISNUMBER('Proyección'!$F$21),N('Proyección'!$F$20)>=$E$9),(12-'Proyección'!$F$21)/12,1)),0) -> 0 | R26: =N26+O26+P26-Q26 -> 81096 | S26: =L26 -> 0 | T26: =G26 -> 0 | U26: =Q26 -> 0
B27: 9 | C27: ='Proyección'!B38 -> 2034 | D27: =H26 -> 71603 | E27: =IF(AND(B27<=$E$7,B27<$F$12),$D$12*12*(1+$E$6)^(B27-1),0) -> 4156 | F27: =D27*$E$5 -> 4296 | G27: =IF(B27>=$F$12,IF(($I$12-$E$9-B27+2)<=1,D27+F27,IF($E$5=0,D27/($I$12-$E$9-B27+2),D27*$E$5/(1-(1+$E$5)^(-($I$12-$E$9-B27+2))))*IF(AND(B27=$F$12,ISNUMBER('Proyección'!$F$21),N('Proyección'!$F$20)>=$E$9),(12-'Proyección'!$F$21)/12,1)),0) -> 0 | H27: =D27+E27+F27-G27 -> 80055 | I27: =M26 -> 51606 | J27: =IF(AND(B27<=$E$7),$D$13*12*(1+$E$6)^(B27-1),0) -> 1467 | K27: =I27*$E$5 -> 3096 | L27: =IF(OR(B27=$F$13,B27=$E$8,B27=50),I27+J27+K27,0) -> 0 | M27: =I27+J27+K27-L27 -> 56169 | N27: =R26 -> 81096 | O27: =IF(AND(B27<=$E$7,B27<$F$14),$D$14*12*(1+$E$10)^(B27-1),0) -> 5432 | P27: =N27*$E$5 -> 4866 | Q27: =IF(B27>=$F$14,IF(($I$14-$E$9-B27+2)<=1,N27+P27,IF($E$5=0,N27/($I$14-$E$9-B27+2),N27*$E$5/(1-(1+$E$5)^(-($I$14-$E$9-B27+2))))*IF(AND(B27=$F$14,ISNUMBER('Proyección'!$F$21),N('Proyección'!$F$20)>=$E$9),(12-'Proyección'!$F$21)/12,1)),0) -> 0 | R27: =N27+O27+P27-Q27 -> 91394 | S27: =L27 -> 0 | T27: =G27 -> 0 | U27: =Q27 -> 0
B28: 10 | C28: ='Proyección'!B39 -> 2035 | D28: =H27 -> 80055 | E28: =IF(AND(B28<=$E$7,B28<$F$12),$D$12*12*(1+$E$6)^(B28-1),0) -> 4318 | F28: =D28*$E$5 -> 4803 | G28: =IF(B28>=$F$12,IF(($I$12-$E$9-B28+2)<=1,D28+F28,IF($E$5=0,D28/($I$12-$E$9-B28+2),D28*$E$5/(1-(1+$E$5)^(-($I$12-$E$9-B28+2))))*IF(AND(B28=$F$12,ISNUMBER('Proyección'!$F$21),N('Proyección'!$F$20)>=$E$9),(12-'Proyección'!$F$21)/12,1)),0) -> 0 | H28: =D28+E28+F28-G28 -> 89176 | I28: =M27 -> 56169 | J28: =IF(AND(B28<=$E$7),$D$13*12*(1+$E$6)^(B28-1),0) -> 1524 | K28: =I28*$E$5 -> 3370 | L28: =IF(OR(B28=$F$13,B28=$E$8,B28=50),I28+J28+K28,0) -> 0 | M28: =I28+J28+K28-L28 -> 61063 | N28: =R27 -> 91394 | O28: =IF(AND(B28<=$E$7,B28<$F$14),$D$14*12*(1+$E$10)^(B28-1),0) -> 5644 | P28: =N28*$E$5 -> 5484 | Q28: =IF(B28>=$F$14,IF(($I$14-$E$9-B28+2)<=1,N28+P28,IF($E$5=0,N28/($I$14-$E$9-B28+2),N28*$E$5/(1-(1+$E$5)^(-($I$14-$E$9-B28+2))))*IF(AND(B28=$F$14,ISNUMBER('Proyección'!$F$21),N('Proyección'!$F$20)>=$E$9),(12-'Proyección'!$F$21)/12,1)),0) -> 0 | R28: =N28+O28+P28-Q28 -> 102522 | S28: =L28 -> 0 | T28: =G28 -> 0 | U28: =Q28 -> 0
B29: 11 | C29: ='Proyección'!B40 -> 2036 | D29: =H28 -> 89176 | E29: =IF(AND(B29<=$E$7,B29<$F$12),$D$12*12*(1+$E$6)^(B29-1),0) -> 4486 | F29: =D29*$E$5 -> 5351 | G29: =IF(B29>=$F$12,IF(($I$12-$E$9-B29+2)<=1,D29+F29,IF($E$5=0,D29/($I$12-$E$9-B29+2),D29*$E$5/(1-(1+$E$5)^(-($I$12-$E$9-B29+2))))*IF(AND(B29=$F$12,ISNUMBER('Proyección'!$F$21),N('Proyección'!$F$20)>=$E$9),(12-'Proyección'!$F$21)/12,1)),0) -> 0 | H29: =D29+E29+F29-G29 -> 99012 | I29: =M28 -> 61063 | J29: =IF(AND(B29<=$E$7),$D$13*12*(1+$E$6)^(B29-1),0) -> 1583 | K29: =I29*$E$5 -> 3664 | L29: =IF(OR(B29=$F$13,B29=$E$8,B29=50),I29+J29+K29,0) -> 0 | M29: =I29+J29+K29-L29 -> 66310 | N29: =R28 -> 102522 | O29: =IF(AND(B29<=$E$7,B29<$F$14),$D$14*12*(1+$E$10)^(B29-1),0) -> 5864 | P29: =N29*$E$5 -> 6151 | Q29: =IF(B29>=$F$14,IF(($I$14-$E$9-B29+2)<=1,N29+P29,IF($E$5=0,N29/($I$14-$E$9-B29+2),N29*$E$5/(1-(1+$E$5)^(-($I$14-$E$9-B29+2))))*IF(AND(B29=$F$14,ISNUMBER('Proyección'!$F$21),N('Proyección'!$F$20)>=$E$9),(12-'Proyección'!$F$21)/12,1)),0) -> 0 | R29: =N29+O29+P29-Q29 -> 114538 | S29: =L29 -> 0 | T29: =G29 -> 0 | U29: =Q29 -> 0
B30: 12 | C30: ='Proyección'!B41 -> 2037 | D30: =H29 -> 99012 | E30: =IF(AND(B30<=$E$7,B30<$F$12),$D$12*12*(1+$E$6)^(B30-1),0) -> 4661 | F30: =D30*$E$5 -> 5941 | G30: =IF(B30>=$F$12,IF(($I$12-$E$9-B30+2)<=1,D30+F30,IF($E$5=0,D30/($I$12-$E$9-B30+2),D30*$E$5/(1-(1+$E$5)^(-($I$12-$E$9-B30+2))))*IF(AND(B30=$F$12,ISNUMBER('Proyección'!$F$21),N('Proyección'!$F$20)>=$E$9),(12-'Proyección'!$F$21)/12,1)),0) -> 0 | H30: =D30+E30+F30-G30 -> 109614 | I30: =M29 -> 66310 | J30: =IF(AND(B30<=$E$7),$D$13*12*(1+$E$6)^(B30-1),0) -> 1645 | K30: =I30*$E$5 -> 3979 | L30: =IF(OR(B30=$F$13,B30=$E$8,B30=50),I30+J30+K30,0) -> 0 | M30: =I30+J30+K30-L30 -> 71934 | N30: =R29 -> 114538 | O30: =IF(AND(B30<=$E$7,B30<$F$14),$D$14*12*(1+$E$10)^(B30-1),0) -> 6093 | P30: =N30*$E$5 -> 6872 | Q30: =IF(B30>=$F$14,IF(($I$14-$E$9-B30+2)<=1,N30+P30,IF($E$5=0,N30/($I$14-$E$9-B30+2),N30*$E$5/(1-(1+$E$5)^(-($I$14-$E$9-B30+2))))*IF(AND(B30=$F$14,ISNUMBER('Proyección'!$F$21),N('Proyección'!$F$20)>=$E$9),(12-'Proyección'!$F$21)/12,1)),0) -> 0 | R30: =N30+O30+P30-Q30 -> 127503 | S30: =L30 -> 0 | T30: =G30 -> 0 | U30: =Q30 -> 0
B31: 13 | C31: ='Proyección'!B42 -> 2038 | D31: =H30 -> 109614 | E31: =IF(AND(B31<=$E$7,B31<$F$12),$D$12*12*(1+$E$6)^(B31-1),0) -> 4843 | F31: =D31*$E$5 -> 6577 | G31: =IF(B31>=$F$12,IF(($I$12-$E$9-B31+2)<=1,D31+F31,IF($E$5=0,D31/($I$12-$E$9-B31+2),D31*$E$5/(1-(1+$E$5)^(-($I$12-$E$9-B31+2))))*IF(AND(B31=$F$12,ISNUMBER('Proyección'!$F$21),N('Proyección'!$F$20)>=$E$9),(12-'Proyección'!$F$21)/12,1)),0) -> 0 | H31: =D31+E31+F31-G31 -> 121034 | I31: =M30 -> 71934 | J31: =IF(AND(B31<=$E$7),$D$13*12*(1+$E$6)^(B31-1),0) -> 1709 | K31: =I31*$E$5 -> 4316 | L31: =IF(OR(B31=$F$13,B31=$E$8,B31=50),I31+J31+K31,0) -> 0 | M31: =I31+J31+K31-L31 -> 77959 | N31: =R30 -> 127503 | O31: =IF(AND(B31<=$E$7,B31<$F$14),$D$14*12*(1+$E$10)^(B31-1),0) -> 6331 | P31: =N31*$E$5 -> 7650 | Q31: =IF(B31>=$F$14,IF(($I$14-$E$9-B31+2)<=1,N31+P31,IF($E$5=0,N31/($I$14-$E$9-B31+2),N31*$E$5/(1-(1+$E$5)^(-($I$14-$E$9-B31+2))))*IF(AND(B31=$F$14,ISNUMBER('Proyección'!$F$21),N('Proyección'!$F$20)>=$E$9),(12-'Proyección'!$F$21)/12,1)),0) -> 0 | R31: =N31+O31+P31-Q31 -> 141484 | S31: =L31 -> 0 | T31: =G31 -> 0 | U31: =Q31 -> 0
... B68: 50 | C68: ='Proyección'!B79 -> 2075 | D68: =H67 -> 61732 | E68: =IF(AND(B68<=$E$7,B68<$F$12),$D$12*12*(1+$E$6)^(B68-1),0) -> 0 | F68: =D68*$E$5 -> 3704 | G68: =IF(B68>=$F$12,IF(($I$12-$E$9-B68+2)<=1,D68+F68,IF($E$5=0,D68/($I$12-$E$9-B68+2),D68*$E$5/(1-(1+$E$5)^(-($I$12-$E$9-B68+2))))*IF(AND(B68=$F$12,ISNUMBER('Proyección'!$F$21),N('Proyección'!$F$20)>=$E$9),(12-'Proyección'!$F$21)/12,1)),0) -> 12554 | H68: =D68+E68+F68-G68 -> 52882 | I68: =M67 -> 0 | J68: =IF(AND(B68<=$E$7),$D$13*12*(1+$E$6)^(B68-1),0) -> 0 | K68: =I68*$E$5 -> 0 | L68: =IF(OR(B68=$F$13,B68=$E$8,B68=50),I68+J68+K68,0) -> 0 | M68: =I68+J68+K68-L68 -> 0 | N68: =R67 -> 72484 | O68: =IF(AND(B68<=$E$7,B68<$F$14),$D$14*12*(1+$E$10)^(B68-1),0) -> 0 | P68: =N68*$E$5 -> 4349 | Q68: =IF(B68>=$F$14,IF(($I$14-$E$9-B68+2)<=1,N68+P68,IF($E$5=0,N68/($I$14-$E$9-B68+2),N68*$E$5/(1-(1+$E$5)^(-($I$14-$E$9-B68+2))))*IF(AND(B68=$F$14,ISNUMBER('Proyección'!$F$21),N('Proyección'!$F$20)>=$E$9),(12-'Proyección'!$F$21)/12,1)),0) -> 14740 | R68: =N68+O68+P68-Q68 -> 62092 | S68: =L68 -> 0 | T68: =G68 -> 12554 | U68: =Q68 -> 14740

Sheet Datos
A1: Clase | B1: Cartera sugerida | C1: Cartera de equilibrio | E1: Volatilidad | F1: Rendimiento | H1: Cartera | I1: Volatilidad | J1: Rendimiento | L1: Corte conservador–moderado conservador | N1: Corte moderado conservador–moderado | P1: Corte moderado–moderado agresivo | R1: Corte moderado agresivo–agresivo | U1: Componente | V1: Cliente | W1: Capacidad financiera
A2: Renta variable | B2: 0.35 | C2: 0.9 | E2: 0.05824 | F2: 0.05001 | H2: Conservador | I2: 0.05824 | J2: 0.05001 | L2: 0 | M2: 3.75 | N2: 0 | O2: 7.5 | P2: 10 | Q2: 2.5 | R2: 10 | S2: 6.25 | U2: Perfil de riesgo (3,9) | V2: 3.9 | W2: 3.6
A3: Renta fija | B3: 0.475 | C3: 0.05 | E3: 0.058667 | F3: 0.050224 | H3: Moderado conservador | I3: 0.078985 | J3: 0.0585725 | L3: 4.2857 | M3: 0 | N3: 8.5714 | O3: 0 | P3: 1.4286 | Q3: 10 | R3: 5.7143 | S3: 10 | U3: Ingresos totales (5,0) | V3: 5 | W3: 3.6
A4: Efectivo | B4: 0.175 | C4: 0.05 | E4: 0.0591 | F4: 0.050438 | H4: Moderado | I4: 0.104067 | J4: 0.067135 | U4: Gastos totales (3,3) | V4: 3.3 | W4: 3.6
E5: 0.059539 | F5: 0.050652 | H5: Moderado agresivo | I5: 0.137651 | J5: 0.072835 | U5: Inversiones (6,7) | V5: 6.7 | W5: 3.6
A6: Perfil de riesgo | B6: Tolerancia | C6: Apetito | E6: 0.059984 | F6: 0.050866 | H6: Agresivo | I6: 0.174735 | J6: 0.078535 | U6: Desinversiones (6,7) | V6: 6.7 | W6: 3.6
A7: Cliente de ejemplo · Moderado conservador | B7: 3.09 | C7: 4.69 | E7: 0.060435 | F7: 0.05108 | H7: Cartera sugerida | I7: 0.078985 | J7: 0.0585725 | U7: Tamaño del portafolio (0,0) | V7: 0 | W7: 3.6
E8: 0.060891 | F8: 0.051294 | H8: Cartera de equilibrio (máximo disponible) | I8: 0.174735 | J8: 0.078535 | U8: Horizonte (0,0) | V8: 0 | W8: 3.6
A9: Conservador | B9: 1 | C9: 1 | E9: 0.061353 | F9: 0.051508 | H9: Rendimiento de equilibrio | I9: 0 | J9: 0.079181
A10: Moderado conservador | B10: 3 | C10: 3 | E10: 0.06182 | F10: 0.051722 | I10: 0.2 | J10: 0.079181
A11: Moderado | B11: 5 | C11: 5 | E11: 0.062292 | F11: 0.051937
A12: Moderado agresivo | B12: 7 | C12: 7 | E12: 0.06277 | F12: 0.052151
A13: Agresivo | B13: 9 | C13: 9 | E13: 0.063252 | F13: 0.052365
E14: 0.06374 | F14: 0.052579
E15: 0.064232 | F15: 0.052793
E16: 0.064729 | F16: 0.053007
E17: 0.06523 | F17: 0.053221
E18: 0.065736 | F18: 0.053435
E19: 0.066247 | F19: 0.053649
E20: 0.066761 | F20: 0.053863
E21: 0.06728 | F21: 0.054077
E22: 0.067803 | F22: 0.054291
E23: 0.06833 | F23: 0.054505
E24: 0.06886 | F24: 0.054719
E25: 0.069395 | F25: 0.054933
... E162: 0.174735 | F162: 0.078535
